[
  {
    "time": 0.149,
    "x": 8.0,
    "y": 0.5
  },
  {
    "time": 0.24,
    "x": 7.869,
    "y": 0.5
  },
  {
    "time": 0.254,
    "x": 7.826,
    "y": 0.5
  },
  {
    "time": 0.27,
    "x": 7.768,
    "y": 0.5
  },
  {
    "time": 0.286,
    "x": 7.704,
    "y": 0.5
  },
  {
    "time": 0.302,
    "x": 7.63,
    "y": 0.5
  },
  {
    "time": 0.319,
    "x": 7.545,
    "y": 0.5
  },
  {
    "time": 0.335,
    "x": 7.453,
    "y": 0.5
  },
  {
    "time": 0.351,
    "x": 7.356,
    "y": 0.5
  },
  {
    "time": 0.367,
    "x": 7.254,
    "y": 0.5
  },
  {
    "time": 0.383,
    "x": 7.139,
    "y": 0.5
  },
  {
    "time": 0.399,
    "x": 7.021,
    "y": 0.5
  },
  {
    "time": 0.415,
    "x": 6.895,
    "y": 0.5
  },
  {
    "time": 0.431,
    "x": 6.762,
    "y": 0.5
  },
  {
    "time": 0.447,
    "x": 6.621,
    "y": 0.5
  },
  {
    "time": 0.463,
    "x": 6.473,
    "y": 0.5
  },
  {
    "time": 0.479,
    "x": 6.319,
    "y": 0.5
  },
  {
    "time": 0.495,
    "x": 6.163,
    "y": 0.5
  },
  {
    "time": 0.511,
    "x": 5.994,
    "y": 0.5
  },
  {
    "time": 0.527,
    "x": 5.819,
    "y": 0.5
  },
  {
    "time": 0.544,
    "x": 5.637,
    "y": 0.5
  },
  {
    "time": 0.56,
    "x": 5.451,
    "y": 0.5
  },
  {
    "time": 0.576,
    "x": 5.255,
    "y": 0.5
  },
  {
    "time": 0.592,
    "x": 5.063,
    "y": 0.5
  },
  {
    "time": 0.608,
    "x": 4.865,
    "y": 0.5
  },
  {
    "time": 0.624,
    "x": 4.658,
    "y": 0.5
  },
  {
    "time": 0.64,
    "x": 4.444,
    "y": 0.5
  },
  {
    "time": 0.656,
    "x": 4.228,
    "y": 0.5
  },
  {
    "time": 0.672,
    "x": 4.016,
    "y": 0.5
  },
  {
    "time": 0.688,
    "x": 3.783,
    "y": 0.5
  },
  {
    "time": 0.705,
    "x": 3.552,
    "y": 0.5
  },
  {
    "time": 0.722,
    "x": 3.309,
    "y": 0.5
  },
  {
    "time": 0.737,
    "x": 3.078,
    "y": 0.5
  },
  {
    "time": 0.754,
    "x": 2.832,
    "y": 0.5
  },
  {
    "time": 0.771,
    "x": 2.579,
    "y": 0.5
  },
  {
    "time": 0.786,
    "x": 2.34,
    "y": 0.5
  },
  {
    "time": 0.802,
    "x": 2.101,
    "y": 0.5
  },
  {
    "time": 0.818,
    "x": 1.85,
    "y": 0.5
  },
  {
    "time": 0.835,
    "x": 1.593,
    "y": 0.5
  },
  {
    "time": 0.85,
    "x": 1.342,
    "y": 0.5
  },
  {
    "time": 0.867,
    "x": 1.085,
    "y": 0.5
  },
  {
    "time": 0.883,
    "x": 0.828,
    "y": 0.5
  },
  {
    "time": 0.9,
    "x": 0.564,
    "y": 0.5
  },
  {
    "time": 0.916,
    "x": 0.307,
    "y": 0.5
  },
  {
    "time": 0.931,
    "x": 0.053,
    "y": 0.5
  },
  {
    "time": 0.947,
    "x": -0.203,
    "y": 0.5
  },
  {
    "time": 0.963,
    "x": -0.456,
    "y": 0.5
  },
  {
    "time": 0.979,
    "x": -0.706,
    "y": 0.5
  },
  {
    "time": 0.996,
    "x": -0.974,
    "y": 0.5
  },
  {
    "time": 1.012,
    "x": -1.237,
    "y": 0.5
  },
  {
    "time": 1.028,
    "x": -1.491,
    "y": 0.5
  },
  {
    "time": 1.044,
    "x": -1.74,
    "y": 0.5
  },
  {
    "time": 1.06,
    "x": -1.989,
    "y": 0.5
  },
  {
    "time": 1.076,
    "x": -2.229,
    "y": 0.5
  },
  {
    "time": 1.093,
    "x": -2.484,
    "y": 0.5
  },
  {
    "time": 1.108,
    "x": -2.724,
    "y": 0.5
  },
  {
    "time": 1.125,
    "x": -2.967,
    "y": 0.5
  },
  {
    "time": 1.141,
    "x": -3.208,
    "y": 0.5
  },
  {
    "time": 1.157,
    "x": -3.445,
    "y": 0.5
  },
  {
    "time": 1.173,
    "x": -3.673,
    "y": 0.5
  },
  {
    "time": 1.189,
    "x": -3.897,
    "y": 0.5
  },
  {
    "time": 1.206,
    "x": -4.129,
    "y": 0.5
  },
  {
    "time": 1.222,
    "x": -4.35,
    "y": 0.5
  },
  {
    "time": 1.239,
    "x": -4.571,
    "y": 0.5
  },
  {
    "time": 1.255,
    "x": -4.781,
    "y": 0.5
  },
  {
    "time": 1.272,
    "x": -4.992,
    "y": 0.5
  },
  {
    "time": 1.288,
    "x": -5.194,
    "y": 0.5
  },
  {
    "time": 1.305,
    "x": -5.392,
    "y": 0.5
  },
  {
    "time": 1.32,
    "x": -5.574,
    "y": 0.5
  },
  {
    "time": 1.336,
    "x": -5.753,
    "y": 0.5
  },
  {
    "time": 1.352,
    "x": -5.929,
    "y": 0.5
  },
  {
    "time": 1.368,
    "x": -6.098,
    "y": 0.5
  },
  {
    "time": 1.385,
    "x": -6.265,
    "y": 0.5
  },
  {
    "time": 1.401,
    "x": -6.423,
    "y": 0.5
  },
  {
    "time": 1.417,
    "x": -6.574,
    "y": 0.5
  },
  {
    "time": 1.433,
    "x": -6.717,
    "y": 0.5
  },
  {
    "time": 1.45,
    "x": -6.86,
    "y": 0.5
  },
  {
    "time": 1.466,
    "x": -6.988,
    "y": 0.5
  },
  {
    "time": 1.483,
    "x": -7.114,
    "y": 0.5
  },
  {
    "time": 1.498,
    "x": -7.226,
    "y": 0.5
  },
  {
    "time": 1.514,
    "x": -7.329,
    "y": 0.5
  },
  {
    "time": 1.53,
    "x": -7.43,
    "y": 0.5
  },
  {
    "time": 1.547,
    "x": -7.525,
    "y": 0.5
  },
  {
    "time": 1.563,
    "x": -7.609,
    "y": 0.5
  },
  {
    "time": 1.579,
    "x": -7.685,
    "y": 0.5
  },
  {
    "time": 1.595,
    "x": -7.75,
    "y": 0.5
  },
  {
    "time": 1.611,
    "x": -7.811,
    "y": 0.5
  },
  {
    "time": 1.626,
    "x": -7.859,
    "y": 0.5
  },
  {
    "time": 1.642,
    "x": -7.904,
    "y": 0.5
  },
  {
    "time": 1.659,
    "x": -7.939,
    "y": 0.5
  },
  {
    "time": 1.674,
    "x": -7.967,
    "y": 0.5
  },
  {
    "time": 1.69,
    "x": -7.986,
    "y": 0.5
  },
  {
    "time": 1.707,
    "x": -7.997,
    "y": 0.5
  },
  {
    "time": 1.724,
    "x": -8.0,
    "y": 0.5
  },
  {
    "time": 1.741,
    "x": -7.993,
    "y": 0.5
  },
  {
    "time": 1.756,
    "x": -7.979,
    "y": 0.5
  },
  {
    "time": 1.773,
    "x": -7.956,
    "y": 0.5
  },
  {
    "time": 1.788,
    "x": -7.927,
    "y": 0.5
  },
  {
    "time": 1.804,
    "x": -7.887,
    "y": 0.5
  },
  {
    "time": 1.821,
    "x": -7.839,
    "y": 0.5
  },
  {
    "time": 1.837,
    "x": -7.783,
    "y": 0.5
  },
  {
    "time": 1.852,
    "x": -7.722,
    "y": 0.5
  },
  {
    "time": 1.868,
    "x": -7.653,
    "y": 0.5
  },
  {
    "time": 1.885,
    "x": -7.571,
    "y": 0.5
  },
  {
    "time": 1.901,
    "x": -7.485,
    "y": 0.5
  },
  {
    "time": 1.916,
    "x": -7.394,
    "y": 0.5
  },
  {
    "time": 1.932,
    "x": -7.292,
    "y": 0.5
  },
  {
    "time": 1.949,
    "x": -7.179,
    "y": 0.5
  },
  {
    "time": 1.964,
    "x": -7.065,
    "y": 0.5
  },
  {
    "time": 1.98,
    "x": -6.942,
    "y": 0.5
  },
  {
    "time": 1.996,
    "x": -6.81,
    "y": 0.5
  },
  {
    "time": 2.012,
    "x": -6.673,
    "y": 0.5
  },
  {
    "time": 2.029,
    "x": -6.524,
    "y": 0.5
  },
  {
    "time": 2.046,
    "x": -6.363,
    "y": 0.5
  },
  {
    "time": 2.063,
    "x": -6.196,
    "y": 0.5
  },
  {
    "time": 2.079,
    "x": -6.028,
    "y": 0.5
  },
  {
    "time": 2.096,
    "x": -5.847,
    "y": 0.5
  },
  {
    "time": 2.112,
    "x": -5.665,
    "y": 0.5
  },
  {
    "time": 2.128,
    "x": -5.481,
    "y": 0.5
  },
  {
    "time": 2.146,
    "x": -5.273,
    "y": 0.5
  },
  {
    "time": 2.163,
    "x": -5.062,
    "y": 0.5
  },
  {
    "time": 2.179,
    "x": -4.855,
    "y": 0.5
  },
  {
    "time": 2.196,
    "x": -4.647,
    "y": 0.5
  },
  {
    "time": 2.211,
    "x": -4.439,
    "y": 0.5
  },
  {
    "time": 2.228,
    "x": -4.217,
    "y": 0.5
  },
  {
    "time": 2.244,
    "x": -3.991,
    "y": 0.5
  },
  {
    "time": 2.26,
    "x": -3.773,
    "y": 0.5
  },
  {
    "time": 2.277,
    "x": -3.537,
    "y": 0.5
  },
  {
    "time": 2.292,
    "x": -3.31,
    "y": 0.5
  },
  {
    "time": 2.309,
    "x": -3.07,
    "y": 0.5
  },
  {
    "time": 2.324,
    "x": -2.842,
    "y": 0.5
  },
  {
    "time": 2.34,
    "x": -2.598,
    "y": 0.5
  },
  {
    "time": 2.356,
    "x": -2.355,
    "y": 0.5
  },
  {
    "time": 2.372,
    "x": -2.105,
    "y": 0.5
  },
  {
    "time": 2.388,
    "x": -1.857,
    "y": 0.5
  },
  {
    "time": 2.404,
    "x": -1.614,
    "y": 0.5
  },
  {
    "time": 2.42,
    "x": -1.355,
    "y": 0.5
  },
  {
    "time": 2.436,
    "x": -1.108,
    "y": 0.5
  },
  {
    "time": 2.452,
    "x": -0.851,
    "y": 0.5
  },
  {
    "time": 2.468,
    "x": -0.601,
    "y": 0.5
  },
  {
    "time": 2.484,
    "x": -0.338,
    "y": 0.5
  },
  {
    "time": 2.501,
    "x": -0.076,
    "y": 0.5
  },
  {
    "time": 2.517,
    "x": 0.188,
    "y": 0.5
  },
  {
    "time": 2.533,
    "x": 0.445,
    "y": 0.5
  },
  {
    "time": 2.549,
    "x": 0.694,
    "y": 0.5
  },
  {
    "time": 2.565,
    "x": 0.957,
    "y": 0.5
  },
  {
    "time": 2.581,
    "x": 1.205,
    "y": 0.5
  },
  {
    "time": 2.597,
    "x": 1.458,
    "y": 0.5
  },
  {
    "time": 2.613,
    "x": 1.708,
    "y": 0.5
  },
  {
    "time": 2.629,
    "x": 1.952,
    "y": 0.5
  },
  {
    "time": 2.646,
    "x": 2.214,
    "y": 0.5
  },
  {
    "time": 2.662,
    "x": 2.466,
    "y": 0.5
  },
  {
    "time": 2.678,
    "x": 2.708,
    "y": 0.5
  },
  {
    "time": 2.695,
    "x": 2.954,
    "y": 0.5
  },
  {
    "time": 2.71,
    "x": 3.187,
    "y": 0.5
  },
  {
    "time": 2.726,
    "x": 3.42,
    "y": 0.5
  },
  {
    "time": 2.742,
    "x": 3.645,
    "y": 0.5
  },
  {
    "time": 2.758,
    "x": 3.876,
    "y": 0.5
  },
  {
    "time": 2.774,
    "x": 4.098,
    "y": 0.5
  },
  {
    "time": 2.791,
    "x": 4.319,
    "y": 0.5
  },
  {
    "time": 2.807,
    "x": 4.532,
    "y": 0.5
  },
  {
    "time": 2.823,
    "x": 4.739,
    "y": 0.5
  },
  {
    "time": 2.838,
    "x": 4.938,
    "y": 0.5
  },
  {
    "time": 2.854,
    "x": 5.135,
    "y": 0.5
  },
  {
    "time": 2.87,
    "x": 5.329,
    "y": 0.5
  },
  {
    "time": 2.886,
    "x": 5.519,
    "y": 0.5
  },
  {
    "time": 2.902,
    "x": 5.703,
    "y": 0.5
  },
  {
    "time": 2.919,
    "x": 5.883,
    "y": 0.5
  },
  {
    "time": 2.935,
    "x": 6.054,
    "y": 0.5
  },
  {
    "time": 2.95,
    "x": 6.21,
    "y": 0.5
  },
  {
    "time": 2.966,
    "x": 6.372,
    "y": 0.5
  },
  {
    "time": 2.982,
    "x": 6.524,
    "y": 0.5
  },
  {
    "time": 2.999,
    "x": 6.671,
    "y": 0.5
  },
  {
    "time": 3.015,
    "x": 6.814,
    "y": 0.5
  },
  {
    "time": 3.032,
    "x": 6.948,
    "y": 0.5
  },
  {
    "time": 3.051,
    "x": 7.098,
    "y": 0.5
  },
  {
    "time": 3.068,
    "x": 7.215,
    "y": 0.5
  },
  {
    "time": 3.084,
    "x": 7.322,
    "y": 0.5
  },
  {
    "time": 3.099,
    "x": 7.418,
    "y": 0.5
  },
  {
    "time": 3.116,
    "x": 7.512,
    "y": 0.5
  },
  {
    "time": 3.131,
    "x": 7.596,
    "y": 0.5
  },
  {
    "time": 3.148,
    "x": 7.673,
    "y": 0.5
  },
  {
    "time": 3.164,
    "x": 7.742,
    "y": 0.5
  },
  {
    "time": 3.179,
    "x": 7.8,
    "y": 0.5
  },
  {
    "time": 3.196,
    "x": 7.855,
    "y": 0.5
  },
  {
    "time": 3.212,
    "x": 7.899,
    "y": 0.5
  },
  {
    "time": 3.227,
    "x": 7.936,
    "y": 0.5
  },
  {
    "time": 3.243,
    "x": 7.963,
    "y": 0.5
  },
  {
    "time": 3.26,
    "x": 7.984,
    "y": 0.5
  },
  {
    "time": 3.275,
    "x": 7.996,
    "y": 0.5
  },
  {
    "time": 3.291,
    "x": 8.0,
    "y": 0.5
  },
  {
    "time": 3.308,
    "x": 7.996,
    "y": 0.5
  },
  {
    "time": 3.323,
    "x": 7.983,
    "y": 0.5
  },
  {
    "time": 3.34,
    "x": 7.962,
    "y": 0.5
  },
  {
    "time": 3.355,
    "x": 7.934,
    "y": 0.5
  },
  {
    "time": 3.372,
    "x": 7.896,
    "y": 0.5
  },
  {
    "time": 3.387,
    "x": 7.851,
    "y": 0.5
  },
  {
    "time": 3.404,
    "x": 7.798,
    "y": 0.5
  },
  {
    "time": 3.419,
    "x": 7.738,
    "y": 0.5
  },
  {
    "time": 3.436,
    "x": 7.667,
    "y": 0.5
  },
  {
    "time": 3.451,
    "x": 7.593,
    "y": 0.5
  },
  {
    "time": 3.468,
    "x": 7.505,
    "y": 0.5
  },
  {
    "time": 3.484,
    "x": 7.409,
    "y": 0.5
  },
  {
    "time": 3.5,
    "x": 7.311,
    "y": 0.5
  },
  {
    "time": 3.517,
    "x": 7.197,
    "y": 0.5
  },
  {
    "time": 3.534,
    "x": 7.074,
    "y": 0.5
  },
  {
    "time": 3.55,
    "x": 6.947,
    "y": 0.5
  },
  {
    "time": 3.567,
    "x": 6.816,
    "y": 0.5
  },
  {
    "time": 3.582,
    "x": 6.679,
    "y": 0.5
  },
  {
    "time": 3.599,
    "x": 6.533,
    "y": 0.5
  },
  {
    "time": 3.614,
    "x": 6.386,
    "y": 0.5
  },
  {
    "time": 3.629,
    "x": 6.239,
    "y": 0.5
  },
  {
    "time": 3.646,
    "x": 6.069,
    "y": 0.5
  },
  {
    "time": 3.661,
    "x": 5.904,
    "y": 0.5
  },
  {
    "time": 3.677,
    "x": 5.727,
    "y": 0.5
  },
  {
    "time": 3.694,
    "x": 5.54,
    "y": 0.5
  },
  {
    "time": 3.71,
    "x": 5.346,
    "y": 0.5
  },
  {
    "time": 3.727,
    "x": 5.151,
    "y": 0.5
  },
  {
    "time": 3.743,
    "x": 4.951,
    "y": 0.5
  },
  {
    "time": 3.758,
    "x": 4.75,
    "y": 0.5
  },
  {
    "time": 3.775,
    "x": 4.538,
    "y": 0.5
  },
  {
    "time": 3.792,
    "x": 4.314,
    "y": 0.5
  },
  {
    "time": 3.808,
    "x": 4.096,
    "y": 0.5
  },
  {
    "time": 3.823,
    "x": 3.877,
    "y": 0.5
  },
  {
    "time": 3.839,
    "x": 3.65,
    "y": 0.5
  },
  {
    "time": 3.855,
    "x": 3.424,
    "y": 0.5
  },
  {
    "time": 3.871,
    "x": 3.187,
    "y": 0.5
  },
  {
    "time": 3.888,
    "x": 2.946,
    "y": 0.5
  },
  {
    "time": 3.905,
    "x": 2.694,
    "y": 0.5
  },
  {
    "time": 3.92,
    "x": 2.457,
    "y": 0.5
  },
  {
    "time": 3.936,
    "x": 2.215,
    "y": 0.5
  },
  {
    "time": 3.955,
    "x": 1.926,
    "y": 0.5
  },
  {
    "time": 3.972,
    "x": 1.661,
    "y": 0.5
  },
  {
    "time": 3.988,
    "x": 1.399,
    "y": 0.5
  },
  {
    "time": 4.005,
    "x": 1.143,
    "y": 0.5
  },
  {
    "time": 4.022,
    "x": 0.874,
    "y": 0.5
  },
  {
    "time": 4.038,
    "x": 0.619,
    "y": 0.5
  },
  {
    "time": 4.054,
    "x": 0.363,
    "y": 0.5
  },
  {
    "time": 4.07,
    "x": 0.106,
    "y": 0.5
  },
  {
    "time": 4.085,
    "x": -0.14,
    "y": 0.5
  },
  {
    "time": 4.102,
    "x": -0.404,
    "y": 0.5
  },
  {
    "time": 4.117,
    "x": -0.657,
    "y": 0.5
  },
  {
    "time": 4.133,
    "x": -0.912,
    "y": 0.5
  },
  {
    "time": 4.149,
    "x": -1.166,
    "y": 0.5
  },
  {
    "time": 4.166,
    "x": -1.42,
    "y": 0.5
  },
  {
    "time": 4.182,
    "x": -1.672,
    "y": 0.5
  },
  {
    "time": 4.197,
    "x": -1.919,
    "y": 0.5
  },
  {
    "time": 4.213,
    "x": -2.166,
    "y": 0.5
  },
  {
    "time": 4.23,
    "x": -2.417,
    "y": 0.5
  },
  {
    "time": 4.247,
    "x": -2.672,
    "y": 0.5
  },
  {
    "time": 4.263,
    "x": -2.918,
    "y": 0.5
  },
  {
    "time": 4.28,
    "x": -3.166,
    "y": 0.5
  },
  {
    "time": 4.297,
    "x": -3.414,
    "y": 0.5
  },
  {
    "time": 4.313,
    "x": -3.653,
    "y": 0.5
  },
  {
    "time": 4.33,
    "x": -3.88,
    "y": 0.5
  },
  {
    "time": 4.346,
    "x": -4.105,
    "y": 0.5
  },
  {
    "time": 4.362,
    "x": -4.322,
    "y": 0.5
  },
  {
    "time": 4.378,
    "x": -4.533,
    "y": 0.5
  },
  {
    "time": 4.393,
    "x": -4.736,
    "y": 0.5
  },
  {
    "time": 4.409,
    "x": -4.942,
    "y": 0.5
  },
  {
    "time": 4.426,
    "x": -5.144,
    "y": 0.5
  },
  {
    "time": 4.442,
    "x": -5.342,
    "y": 0.5
  },
  {
    "time": 4.459,
    "x": -5.541,
    "y": 0.5
  },
  {
    "time": 4.476,
    "x": -5.73,
    "y": 0.5
  },
  {
    "time": 4.491,
    "x": -5.904,
    "y": 0.5
  },
  {
    "time": 4.507,
    "x": -6.074,
    "y": 0.5
  },
  {
    "time": 4.524,
    "x": -6.24,
    "y": 0.5
  },
  {
    "time": 4.54,
    "x": -6.396,
    "y": 0.5
  },
  {
    "time": 4.556,
    "x": -6.547,
    "y": 0.5
  },
  {
    "time": 4.571,
    "x": -6.688,
    "y": 0.5
  },
  {
    "time": 4.588,
    "x": -6.828,
    "y": 0.5
  },
  {
    "time": 4.603,
    "x": -6.952,
    "y": 0.5
  },
  {
    "time": 4.619,
    "x": -7.078,
    "y": 0.5
  },
  {
    "time": 4.635,
    "x": -7.192,
    "y": 0.5
  },
  {
    "time": 4.652,
    "x": -7.303,
    "y": 0.5
  },
  {
    "time": 4.668,
    "x": -7.405,
    "y": 0.5
  },
  {
    "time": 4.684,
    "x": -7.497,
    "y": 0.5
  },
  {
    "time": 4.7,
    "x": -7.583,
    "y": 0.5
  },
  {
    "time": 4.716,
    "x": -7.662,
    "y": 0.5
  },
  {
    "time": 4.732,
    "x": -7.734,
    "y": 0.5
  },
  {
    "time": 4.749,
    "x": -7.797,
    "y": 0.5
  },
  {
    "time": 4.765,
    "x": -7.851,
    "y": 0.5
  },
  {
    "time": 4.782,
    "x": -7.898,
    "y": 0.5
  },
  {
    "time": 4.798,
    "x": -7.934,
    "y": 0.5
  },
  {
    "time": 4.813,
    "x": -7.962,
    "y": 0.5
  },
  {
    "time": 4.83,
    "x": -7.984,
    "y": 0.5
  },
  {
    "time": 4.846,
    "x": -7.996,
    "y": 0.5
  },
  {
    "time": 4.862,
    "x": -8.0,
    "y": 0.5
  },
  {
    "time": 4.879,
    "x": -7.995,
    "y": 0.5
  },
  {
    "time": 4.895,
    "x": -7.982,
    "y": 0.5
  },
  {
    "time": 4.912,
    "x": -7.96,
    "y": 0.5
  },
  {
    "time": 4.929,
    "x": -7.928,
    "y": 0.5
  },
  {
    "time": 4.945,
    "x": -7.89,
    "y": 0.5
  },
  {
    "time": 4.96,
    "x": -7.846,
    "y": 0.5
  },
  {
    "time": 4.977,
    "x": -7.788,
    "y": 0.5
  },
  {
    "time": 4.994,
    "x": -7.722,
    "y": 0.5
  },
  {
    "time": 5.011,
    "x": -7.649,
    "y": 0.5
  },
  {
    "time": 5.027,
    "x": -7.568,
    "y": 0.5
  },
  {
    "time": 5.043,
    "x": -7.478,
    "y": 0.5
  },
  {
    "time": 5.06,
    "x": -7.38,
    "y": 0.5
  },
  {
    "time": 5.076,
    "x": -7.274,
    "y": 0.5
  },
  {
    "time": 5.092,
    "x": -7.165,
    "y": 0.5
  },
  {
    "time": 5.108,
    "x": -7.046,
    "y": 0.5
  },
  {
    "time": 5.125,
    "x": -6.917,
    "y": 0.5
  },
  {
    "time": 5.141,
    "x": -6.782,
    "y": 0.5
  },
  {
    "time": 5.162,
    "x": -6.603,
    "y": 0.5
  },
  {
    "time": 5.178,
    "x": -6.456,
    "y": 0.5
  },
  {
    "time": 5.194,
    "x": -6.3,
    "y": 0.5
  },
  {
    "time": 5.21,
    "x": -6.14,
    "y": 0.5
  },
  {
    "time": 5.225,
    "x": -5.977,
    "y": 0.5
  },
  {
    "time": 5.241,
    "x": -5.803,
    "y": 0.5
  },
  {
    "time": 5.259,
    "x": -5.602,
    "y": 0.5
  },
  {
    "time": 5.276,
    "x": -5.409,
    "y": 0.5
  },
  {
    "time": 5.293,
    "x": -5.205,
    "y": 0.5
  },
  {
    "time": 5.309,
    "x": -5.003,
    "y": 0.5
  },
  {
    "time": 5.326,
    "x": -4.796,
    "y": 0.5
  },
  {
    "time": 5.342,
    "x": -4.586,
    "y": 0.5
  },
  {
    "time": 5.358,
    "x": -4.368,
    "y": 0.5
  },
  {
    "time": 5.375,
    "x": -4.149,
    "y": 0.5
  },
  {
    "time": 5.391,
    "x": -3.926,
    "y": 0.5
  },
  {
    "time": 5.406,
    "x": -3.705,
    "y": 0.5
  },
  {
    "time": 5.422,
    "x": -3.477,
    "y": 0.5
  },
  {
    "time": 5.438,
    "x": -3.247,
    "y": 0.5
  },
  {
    "time": 5.454,
    "x": -3.007,
    "y": 0.5
  },
  {
    "time": 5.47,
    "x": -2.774,
    "y": 0.5
  },
  {
    "time": 5.487,
    "x": -2.521,
    "y": 0.5
  },
  {
    "time": 5.504,
    "x": -2.264,
    "y": 0.5
  },
  {
    "time": 5.519,
    "x": -2.02,
    "y": 0.5
  },
  {
    "time": 5.535,
    "x": -1.775,
    "y": 0.5
  },
  {
    "time": 5.552,
    "x": -1.51,
    "y": 0.5
  },
  {
    "time": 5.568,
    "x": -1.257,
    "y": 0.5
  },
  {
    "time": 5.584,
    "x": -1.001,
    "y": 0.5
  },
  {
    "time": 5.6,
    "x": -0.751,
    "y": 0.5
  },
  {
    "time": 5.616,
    "x": -0.496,
    "y": 0.5
  },
  {
    "time": 5.632,
    "x": -0.247,
    "y": 0.5
  },
  {
    "time": 5.649,
    "x": 0.025,
    "y": 0.5
  },
  {
    "time": 5.664,
    "x": 0.275,
    "y": 0.5
  },
  {
    "time": 5.68,
    "x": 0.532,
    "y": 0.5
  },
  {
    "time": 5.697,
    "x": 0.791,
    "y": 0.5
  },
  {
    "time": 5.712,
    "x": 1.04,
    "y": 0.5
  },
  {
    "time": 5.729,
    "x": 1.296,
    "y": 0.5
  },
  {
    "time": 5.745,
    "x": 1.555,
    "y": 0.5
  },
  {
    "time": 5.762,
    "x": 1.816,
    "y": 0.5
  },
  {
    "time": 5.778,
    "x": 2.069,
    "y": 0.5
  },
  {
    "time": 5.794,
    "x": 2.322,
    "y": 0.5
  },
  {
    "time": 5.81,
    "x": 2.561,
    "y": 0.5
  },
  {
    "time": 5.827,
    "x": 2.812,
    "y": 0.5
  },
  {
    "time": 5.842,
    "x": 3.044,
    "y": 0.5
  },
  {
    "time": 5.858,
    "x": 3.277,
    "y": 0.5
  },
  {
    "time": 5.875,
    "x": 3.518,
    "y": 0.5
  },
  {
    "time": 5.89,
    "x": 3.738,
    "y": 0.5
  },
  {
    "time": 5.907,
    "x": 3.969,
    "y": 0.5
  },
  {
    "time": 5.923,
    "x": 4.189,
    "y": 0.5
  },
  {
    "time": 5.938,
    "x": 4.401,
    "y": 0.5
  },
  {
    "time": 5.954,
    "x": 4.61,
    "y": 0.5
  },
  {
    "time": 5.97,
    "x": 4.815,
    "y": 0.5
  },
  {
    "time": 5.986,
    "x": 5.021,
    "y": 0.5
  },
  {
    "time": 6.002,
    "x": 5.217,
    "y": 0.5
  },
  {
    "time": 6.02,
    "x": 5.424,
    "y": 0.5
  },
  {
    "time": 6.035,
    "x": 5.601,
    "y": 0.5
  },
  {
    "time": 6.052,
    "x": 5.788,
    "y": 0.5
  },
  {
    "time": 6.067,
    "x": 5.96,
    "y": 0.5
  },
  {
    "time": 6.083,
    "x": 6.128,
    "y": 0.5
  },
  {
    "time": 6.099,
    "x": 6.289,
    "y": 0.5
  },
  {
    "time": 6.116,
    "x": 6.445,
    "y": 0.5
  },
  {
    "time": 6.131,
    "x": 6.589,
    "y": 0.5
  },
  {
    "time": 6.147,
    "x": 6.734,
    "y": 0.5
  },
  {
    "time": 6.164,
    "x": 6.873,
    "y": 0.5
  },
  {
    "time": 6.181,
    "x": 7.007,
    "y": 0.5
  },
  {
    "time": 6.197,
    "x": 7.126,
    "y": 0.5
  },
  {
    "time": 6.212,
    "x": 7.237,
    "y": 0.5
  },
  {
    "time": 6.229,
    "x": 7.343,
    "y": 0.5
  },
  {
    "time": 6.244,
    "x": 7.438,
    "y": 0.5
  },
  {
    "time": 6.26,
    "x": 7.529,
    "y": 0.5
  },
  {
    "time": 6.276,
    "x": 7.612,
    "y": 0.5
  },
  {
    "time": 6.292,
    "x": 7.687,
    "y": 0.5
  },
  {
    "time": 6.309,
    "x": 7.755,
    "y": 0.5
  },
  {
    "time": 6.325,
    "x": 7.815,
    "y": 0.5
  },
  {
    "time": 6.342,
    "x": 7.868,
    "y": 0.5
  },
  {
    "time": 6.358,
    "x": 7.911,
    "y": 0.5
  },
  {
    "time": 6.373,
    "x": 7.944,
    "y": 0.5
  },
  {
    "time": 6.39,
    "x": 7.971,
    "y": 0.5
  },
  {
    "time": 6.407,
    "x": 7.99,
    "y": 0.5
  },
  {
    "time": 6.424,
    "x": 7.999,
    "y": 0.5
  },
  {
    "time": 6.441,
    "x": 7.999,
    "y": 0.5
  },
  {
    "time": 6.458,
    "x": 7.99,
    "y": 0.5
  },
  {
    "time": 6.474,
    "x": 7.972,
    "y": 0.5
  },
  {
    "time": 6.491,
    "x": 7.946,
    "y": 0.5
  }
]