[
  {
    "time": 146.11,
    "x": -7.871,
    "y": 0.5
  },
  {
    "time": 146.126,
    "x": -7.912,
    "y": 0.5
  },
  {
    "time": 146.142,
    "x": -7.946,
    "y": 0.5
  },
  {
    "time": 146.158,
    "x": -7.972,
    "y": 0.5
  },
  {
    "time": 146.174,
    "x": -7.989,
    "y": 0.5
  },
  {
    "time": 146.19,
    "x": -7.998,
    "y": 0.5
  },
  {
    "time": 146.206,
    "x": -8.0,
    "y": 0.5
  },
  {
    "time": 146.222,
    "x": -7.992,
    "y": 0.5
  },
  {
    "time": 146.239,
    "x": -7.976,
    "y": 0.5
  },
  {
    "time": 146.255,
    "x": -7.951,
    "y": 0.5
  },
  {
    "time": 146.272,
    "x": -7.917,
    "y": 0.5
  },
  {
    "time": 146.288,
    "x": -7.877,
    "y": 0.5
  },
  {
    "time": 146.304,
    "x": -7.829,
    "y": 0.5
  },
  {
    "time": 146.32,
    "x": -7.772,
    "y": 0.5
  },
  {
    "time": 146.336,
    "x": -7.707,
    "y": 0.5
  },
  {
    "time": 146.352,
    "x": -7.635,
    "y": 0.5
  },
  {
    "time": 146.368,
    "x": -7.552,
    "y": 0.5
  },
  {
    "time": 146.384,
    "x": -7.464,
    "y": 0.5
  },
  {
    "time": 146.4,
    "x": -7.368,
    "y": 0.5
  },
  {
    "time": 146.416,
    "x": -7.266,
    "y": 0.5
  },
  {
    "time": 146.432,
    "x": -7.157,
    "y": 0.5
  },
  {
    "time": 146.448,
    "x": -7.04,
    "y": 0.5
  },
  {
    "time": 146.464,
    "x": -6.911,
    "y": 0.5
  },
  {
    "time": 146.48,
    "x": -6.782,
    "y": 0.5
  },
  {
    "time": 146.496,
    "x": -6.64,
    "y": 0.5
  },
  {
    "time": 146.512,
    "x": -6.495,
    "y": 0.5
  },
  {
    "time": 146.528,
    "x": -6.338,
    "y": 0.5
  },
  {
    "time": 146.544,
    "x": -6.183,
    "y": 0.5
  },
  {
    "time": 146.56,
    "x": -6.018,
    "y": 0.5
  },
  {
    "time": 146.576,
    "x": -5.839,
    "y": 0.5
  },
  {
    "time": 146.593,
    "x": -5.655,
    "y": 0.5
  },
  {
    "time": 146.609,
    "x": -5.473,
    "y": 0.5
  },
  {
    "time": 146.625,
    "x": -5.277,
    "y": 0.5
  },
  {
    "time": 146.642,
    "x": -5.073,
    "y": 0.5
  },
  {
    "time": 146.657,
    "x": -4.88,
    "y": 0.5
  },
  {
    "time": 146.674,
    "x": -4.671,
    "y": 0.5
  },
  {
    "time": 146.69,
    "x": -4.459,
    "y": 0.5
  },
  {
    "time": 146.706,
    "x": -4.242,
    "y": 0.5
  },
  {
    "time": 146.722,
    "x": -4.025,
    "y": 0.5
  },
  {
    "time": 146.738,
    "x": -3.8,
    "y": 0.5
  },
  {
    "time": 146.753,
    "x": -3.579,
    "y": 0.5
  },
  {
    "time": 146.77,
    "x": -3.344,
    "y": 0.5
  },
  {
    "time": 146.786,
    "x": -3.102,
    "y": 0.5
  },
  {
    "time": 146.803,
    "x": -2.848,
    "y": 0.5
  },
  {
    "time": 146.82,
    "x": -2.603,
    "y": 0.5
  },
  {
    "time": 146.835,
    "x": -2.364,
    "y": 0.5
  },
  {
    "time": 146.852,
    "x": -2.108,
    "y": 0.5
  },
  {
    "time": 146.868,
    "x": -1.862,
    "y": 0.5
  },
  {
    "time": 146.884,
    "x": -1.612,
    "y": 0.5
  },
  {
    "time": 146.9,
    "x": -1.364,
    "y": 0.5
  },
  {
    "time": 146.916,
    "x": -1.107,
    "y": 0.5
  },
  {
    "time": 146.932,
    "x": -0.858,
    "y": 0.5
  },
  {
    "time": 146.948,
    "x": -0.594,
    "y": 0.5
  },
  {
    "time": 146.965,
    "x": -0.33,
    "y": 0.5
  },
  {
    "time": 146.98,
    "x": -0.081,
    "y": 0.5
  },
  {
    "time": 146.997,
    "x": 0.178,
    "y": 0.5
  },
  {
    "time": 147.013,
    "x": 0.44,
    "y": 0.5
  },
  {
    "time": 147.029,
    "x": 0.691,
    "y": 0.5
  },
  {
    "time": 147.045,
    "x": 0.947,
    "y": 0.5
  },
  {
    "time": 147.061,
    "x": 1.2,
    "y": 0.5
  },
  {
    "time": 147.077,
    "x": 1.462,
    "y": 0.5
  },
  {
    "time": 147.094,
    "x": 1.723,
    "y": 0.5
  },
  {
    "time": 147.11,
    "x": 1.974,
    "y": 0.5
  },
  {
    "time": 147.126,
    "x": 2.218,
    "y": 0.5
  },
  {
    "time": 147.142,
    "x": 2.466,
    "y": 0.5
  },
  {
    "time": 147.158,
    "x": 2.702,
    "y": 0.5
  },
  {
    "time": 147.174,
    "x": 2.945,
    "y": 0.5
  },
  {
    "time": 147.189,
    "x": 3.174,
    "y": 0.5
  },
  {
    "time": 147.206,
    "x": 3.415,
    "y": 0.5
  },
  {
    "time": 147.222,
    "x": 3.643,
    "y": 0.5
  },
  {
    "time": 147.238,
    "x": 3.876,
    "y": 0.5
  },
  {
    "time": 147.255,
    "x": 4.109,
    "y": 0.5
  },
  {
    "time": 147.271,
    "x": 4.324,
    "y": 0.5
  },
  {
    "time": 147.287,
    "x": 4.538,
    "y": 0.5
  },
  {
    "time": 147.303,
    "x": 4.743,
    "y": 0.5
  },
  {
    "time": 147.319,
    "x": 4.951,
    "y": 0.5
  },
  {
    "time": 147.334,
    "x": 5.142,
    "y": 0.5
  },
  {
    "time": 147.351,
    "x": 5.344,
    "y": 0.5
  },
  {
    "time": 147.367,
    "x": 5.531,
    "y": 0.5
  },
  {
    "time": 147.383,
    "x": 5.708,
    "y": 0.5
  },
  {
    "time": 147.399,
    "x": 5.882,
    "y": 0.5
  },
  {
    "time": 147.415,
    "x": 6.056,
    "y": 0.5
  },
  {
    "time": 147.431,
    "x": 6.226,
    "y": 0.5
  },
  {
    "time": 147.448,
    "x": 6.388,
    "y": 0.5
  },
  {
    "time": 147.464,
    "x": 6.536,
    "y": 0.5
  },
  {
    "time": 147.48,
    "x": 6.684,
    "y": 0.5
  },
  {
    "time": 147.496,
    "x": 6.821,
    "y": 0.5
  },
  {
    "time": 147.512,
    "x": 6.952,
    "y": 0.5
  },
  {
    "time": 147.528,
    "x": 7.075,
    "y": 0.5
  },
  {
    "time": 147.544,
    "x": 7.194,
    "y": 0.5
  },
  {
    "time": 147.561,
    "x": 7.303,
    "y": 0.5
  },
  {
    "time": 147.577,
    "x": 7.405,
    "y": 0.5
  },
  {
    "time": 147.593,
    "x": 7.498,
    "y": 0.5
  },
  {
    "time": 147.609,
    "x": 7.584,
    "y": 0.5
  },
  {
    "time": 147.625,
    "x": 7.662,
    "y": 0.5
  },
  {
    "time": 147.641,
    "x": 7.732,
    "y": 0.5
  },
  {
    "time": 147.657,
    "x": 7.794,
    "y": 0.5
  },
  {
    "time": 147.673,
    "x": 7.848,
    "y": 0.5
  },
  {
    "time": 147.69,
    "x": 7.895,
    "y": 0.5
  },
  {
    "time": 147.706,
    "x": 7.932,
    "y": 0.5
  },
  {
    "time": 147.722,
    "x": 7.962,
    "y": 0.5
  },
  {
    "time": 147.738,
    "x": 7.983,
    "y": 0.5
  },
  {
    "time": 147.754,
    "x": 7.996,
    "y": 0.5
  },
  {
    "time": 147.77,
    "x": 8.0,
    "y": 0.5
  },
  {
    "time": 147.786,
    "x": 7.996,
    "y": 0.5
  },
  {
    "time": 147.803,
    "x": 7.983,
    "y": 0.5
  },
  {
    "time": 147.819,
    "x": 7.963,
    "y": 0.5
  },
  {
    "time": 147.835,
    "x": 7.933,
    "y": 0.5
  },
  {
    "time": 147.852,
    "x": 7.894,
    "y": 0.5
  },
  {
    "time": 147.868,
    "x": 7.849,
    "y": 0.5
  },
  {
    "time": 147.884,
    "x": 7.796,
    "y": 0.5
  },
  {
    "time": 147.9,
    "x": 7.734,
    "y": 0.5
  },
  {
    "time": 147.916,
    "x": 7.664,
    "y": 0.5
  },
  {
    "time": 147.933,
    "x": 7.584,
    "y": 0.5
  },
  {
    "time": 147.949,
    "x": 7.496,
    "y": 0.5
  },
  {
    "time": 147.966,
    "x": 7.4,
    "y": 0.5
  },
  {
    "time": 147.982,
    "x": 7.297,
    "y": 0.5
  },
  {
    "time": 147.998,
    "x": 7.19,
    "y": 0.5
  },
  {
    "time": 148.014,
    "x": 7.071,
    "y": 0.5
  },
  {
    "time": 148.03,
    "x": 6.95,
    "y": 0.5
  },
  {
    "time": 148.046,
    "x": 6.816,
    "y": 0.5
  },
  {
    "time": 148.063,
    "x": 6.674,
    "y": 0.5
  },
  {
    "time": 148.079,
    "x": 6.529,
    "y": 0.5
  },
  {
    "time": 148.095,
    "x": 6.38,
    "y": 0.5
  },
  {
    "time": 148.11,
    "x": 6.224,
    "y": 0.5
  },
  {
    "time": 148.127,
    "x": 6.052,
    "y": 0.5
  },
  {
    "time": 148.143,
    "x": 5.886,
    "y": 0.5
  },
  {
    "time": 148.159,
    "x": 5.709,
    "y": 0.5
  },
  {
    "time": 148.175,
    "x": 5.53,
    "y": 0.5
  },
  {
    "time": 148.191,
    "x": 5.338,
    "y": 0.5
  },
  {
    "time": 148.207,
    "x": 5.149,
    "y": 0.5
  },
  {
    "time": 148.223,
    "x": 4.948,
    "y": 0.5
  },
  {
    "time": 148.239,
    "x": 4.745,
    "y": 0.5
  },
  {
    "time": 148.255,
    "x": 4.537,
    "y": 0.5
  },
  {
    "time": 148.271,
    "x": 4.316,
    "y": 0.5
  },
  {
    "time": 148.287,
    "x": 4.105,
    "y": 0.5
  },
  {
    "time": 148.303,
    "x": 3.876,
    "y": 0.5
  },
  {
    "time": 148.32,
    "x": 3.635,
    "y": 0.5
  },
  {
    "time": 148.337,
    "x": 3.401,
    "y": 0.5
  },
  {
    "time": 148.353,
    "x": 3.16,
    "y": 0.5
  },
  {
    "time": 148.369,
    "x": 2.928,
    "y": 0.5
  },
  {
    "time": 148.385,
    "x": 2.693,
    "y": 0.5
  },
  {
    "time": 148.401,
    "x": 2.439,
    "y": 0.5
  },
  {
    "time": 148.418,
    "x": 2.184,
    "y": 0.5
  },
  {
    "time": 148.433,
    "x": 1.946,
    "y": 0.5
  },
  {
    "time": 148.45,
    "x": 1.688,
    "y": 0.5
  },
  {
    "time": 148.466,
    "x": 1.43,
    "y": 0.5
  },
  {
    "time": 148.483,
    "x": 1.163,
    "y": 0.5
  },
  {
    "time": 148.499,
    "x": 0.914,
    "y": 0.5
  },
  {
    "time": 148.515,
    "x": 0.66,
    "y": 0.5
  },
  {
    "time": 148.531,
    "x": 0.405,
    "y": 0.5
  },
  {
    "time": 148.547,
    "x": 0.151,
    "y": 0.5
  },
  {
    "time": 148.563,
    "x": -0.111,
    "y": 0.5
  },
  {
    "time": 148.579,
    "x": -0.364,
    "y": 0.5
  },
  {
    "time": 148.595,
    "x": -0.62,
    "y": 0.5
  },
  {
    "time": 148.611,
    "x": -0.873,
    "y": 0.5
  },
  {
    "time": 148.627,
    "x": -1.127,
    "y": 0.5
  },
  {
    "time": 148.643,
    "x": -1.379,
    "y": 0.5
  },
  {
    "time": 148.659,
    "x": -1.632,
    "y": 0.5
  },
  {
    "time": 148.675,
    "x": -1.881,
    "y": 0.5
  },
  {
    "time": 148.691,
    "x": -2.135,
    "y": 0.5
  },
  {
    "time": 148.708,
    "x": -2.396,
    "y": 0.5
  },
  {
    "time": 148.725,
    "x": -2.645,
    "y": 0.5
  },
  {
    "time": 148.741,
    "x": -2.888,
    "y": 0.5
  },
  {
    "time": 148.757,
    "x": -3.126,
    "y": 0.5
  },
  {
    "time": 148.773,
    "x": -3.363,
    "y": 0.5
  },
  {
    "time": 148.789,
    "x": -3.59,
    "y": 0.5
  },
  {
    "time": 148.805,
    "x": -3.815,
    "y": 0.5
  },
  {
    "time": 148.821,
    "x": -4.035,
    "y": 0.5
  },
  {
    "time": 148.837,
    "x": -4.257,
    "y": 0.5
  },
  {
    "time": 148.853,
    "x": -4.47,
    "y": 0.5
  },
  {
    "time": 148.869,
    "x": -4.689,
    "y": 0.5
  },
  {
    "time": 148.886,
    "x": -4.904,
    "y": 0.5
  },
  {
    "time": 148.902,
    "x": -5.099,
    "y": 0.5
  },
  {
    "time": 148.918,
    "x": -5.298,
    "y": 0.5
  },
  {
    "time": 148.934,
    "x": -5.482,
    "y": 0.5
  },
  {
    "time": 148.95,
    "x": -5.672,
    "y": 0.5
  },
  {
    "time": 148.967,
    "x": -5.859,
    "y": 0.5
  },
  {
    "time": 148.983,
    "x": -6.025,
    "y": 0.5
  },
  {
    "time": 148.999,
    "x": -6.192,
    "y": 0.5
  },
  {
    "time": 149.015,
    "x": -6.355,
    "y": 0.5
  },
  {
    "time": 149.031,
    "x": -6.505,
    "y": 0.5
  },
  {
    "time": 149.047,
    "x": -6.647,
    "y": 0.5
  },
  {
    "time": 149.063,
    "x": -6.786,
    "y": 0.5
  },
  {
    "time": 149.079,
    "x": -6.922,
    "y": 0.5
  },
  {
    "time": 149.095,
    "x": -7.049,
    "y": 0.5
  },
  {
    "time": 149.112,
    "x": -7.171,
    "y": 0.5
  },
  {
    "time": 149.128,
    "x": -7.284,
    "y": 0.5
  },
  {
    "time": 149.145,
    "x": -7.39,
    "y": 0.5
  },
  {
    "time": 149.161,
    "x": -7.482,
    "y": 0.5
  },
  {
    "time": 149.177,
    "x": -7.569,
    "y": 0.5
  },
  {
    "time": 149.193,
    "x": -7.649,
    "y": 0.5
  },
  {
    "time": 149.209,
    "x": -7.721,
    "y": 0.5
  },
  {
    "time": 149.225,
    "x": -7.785,
    "y": 0.5
  },
  {
    "time": 149.242,
    "x": -7.841,
    "y": 0.5
  },
  {
    "time": 149.258,
    "x": -7.888,
    "y": 0.5
  },
  {
    "time": 149.274,
    "x": -7.927,
    "y": 0.5
  },
  {
    "time": 149.29,
    "x": -7.957,
    "y": 0.5
  },
  {
    "time": 149.306,
    "x": -7.98,
    "y": 0.5
  },
  {
    "time": 149.322,
    "x": -7.994,
    "y": 0.5
  },
  {
    "time": 149.338,
    "x": -8.0,
    "y": 0.5
  },
  {
    "time": 149.354,
    "x": -7.998,
    "y": 0.5
  },
  {
    "time": 149.369,
    "x": -7.988,
    "y": 0.5
  },
  {
    "time": 149.385,
    "x": -7.969,
    "y": 0.5
  },
  {
    "time": 149.402,
    "x": -7.941,
    "y": 0.5
  },
  {
    "time": 149.418,
    "x": -7.906,
    "y": 0.5
  },
  {
    "time": 149.435,
    "x": -7.862,
    "y": 0.5
  },
  {
    "time": 149.451,
    "x": -7.808,
    "y": 0.5
  },
  {
    "time": 149.467,
    "x": -7.751,
    "y": 0.5
  },
  {
    "time": 149.483,
    "x": -7.681,
    "y": 0.5
  },
  {
    "time": 149.499,
    "x": -7.605,
    "y": 0.5
  },
  {
    "time": 149.516,
    "x": -7.519,
    "y": 0.5
  },
  {
    "time": 149.532,
    "x": -7.425,
    "y": 0.5
  },
  {
    "time": 149.549,
    "x": -7.323,
    "y": 0.5
  },
  {
    "time": 149.565,
    "x": -7.218,
    "y": 0.5
  },
  {
    "time": 149.581,
    "x": -7.103,
    "y": 0.5
  },
  {
    "time": 149.597,
    "x": -6.978,
    "y": 0.5
  },
  {
    "time": 149.613,
    "x": -6.853,
    "y": 0.5
  },
  {
    "time": 149.63,
    "x": -6.71,
    "y": 0.5
  },
  {
    "time": 149.646,
    "x": -6.559,
    "y": 0.5
  },
  {
    "time": 149.663,
    "x": -6.4,
    "y": 0.5
  },
  {
    "time": 149.68,
    "x": -6.233,
    "y": 0.5
  },
  {
    "time": 149.697,
    "x": -6.063,
    "y": 0.5
  },
  {
    "time": 149.713,
    "x": -5.898,
    "y": 0.5
  },
  {
    "time": 149.729,
    "x": -5.72,
    "y": 0.5
  },
  {
    "time": 149.745,
    "x": -5.531,
    "y": 0.5
  },
  {
    "time": 149.762,
    "x": -5.332,
    "y": 0.5
  },
  {
    "time": 149.778,
    "x": -5.141,
    "y": 0.5
  },
  {
    "time": 149.794,
    "x": -4.939,
    "y": 0.5
  },
  {
    "time": 149.81,
    "x": -4.739,
    "y": 0.5
  },
  {
    "time": 149.826,
    "x": -4.525,
    "y": 0.5
  },
  {
    "time": 149.843,
    "x": -4.302,
    "y": 0.5
  },
  {
    "time": 149.859,
    "x": -4.087,
    "y": 0.5
  },
  {
    "time": 149.875,
    "x": -3.867,
    "y": 0.5
  },
  {
    "time": 149.891,
    "x": -3.635,
    "y": 0.5
  },
  {
    "time": 149.907,
    "x": -3.41,
    "y": 0.5
  },
  {
    "time": 149.923,
    "x": -3.179,
    "y": 0.5
  },
  {
    "time": 149.939,
    "x": -2.942,
    "y": 0.5
  },
  {
    "time": 149.955,
    "x": -2.699,
    "y": 0.5
  },
  {
    "time": 149.971,
    "x": -2.454,
    "y": 0.5
  },
  {
    "time": 149.987,
    "x": -2.21,
    "y": 0.5
  },
  {
    "time": 150.003,
    "x": -1.969,
    "y": 0.5
  },
  {
    "time": 150.019,
    "x": -1.715,
    "y": 0.5
  },
  {
    "time": 150.035,
    "x": -1.471,
    "y": 0.5
  },
  {
    "time": 150.051,
    "x": -1.214,
    "y": 0.5
  },
  {
    "time": 150.067,
    "x": -0.954,
    "y": 0.5
  },
  {
    "time": 150.083,
    "x": -0.704,
    "y": 0.5
  },
  {
    "time": 150.099,
    "x": -0.443,
    "y": 0.5
  },
  {
    "time": 150.116,
    "x": -0.178,
    "y": 0.5
  },
  {
    "time": 150.132,
    "x": 0.076,
    "y": 0.5
  },
  {
    "time": 150.148,
    "x": 0.337,
    "y": 0.5
  },
  {
    "time": 150.164,
    "x": 0.586,
    "y": 0.5
  },
  {
    "time": 150.18,
    "x": 0.845,
    "y": 0.5
  },
  {
    "time": 150.196,
    "x": 1.105,
    "y": 0.5
  },
  {
    "time": 150.212,
    "x": 1.353,
    "y": 0.5
  },
  {
    "time": 150.228,
    "x": 1.604,
    "y": 0.5
  },
  {
    "time": 150.244,
    "x": 1.854,
    "y": 0.5
  },
  {
    "time": 150.26,
    "x": 2.1,
    "y": 0.5
  },
  {
    "time": 150.276,
    "x": 2.353,
    "y": 0.5
  },
  {
    "time": 150.292,
    "x": 2.595,
    "y": 0.5
  },
  {
    "time": 150.308,
    "x": 2.828,
    "y": 0.5
  },
  {
    "time": 150.324,
    "x": 3.068,
    "y": 0.5
  },
  {
    "time": 150.34,
    "x": 3.305,
    "y": 0.5
  },
  {
    "time": 150.356,
    "x": 3.532,
    "y": 0.5
  },
  {
    "time": 150.372,
    "x": 3.768,
    "y": 0.5
  },
  {
    "time": 150.388,
    "x": 3.992,
    "y": 0.5
  },
  {
    "time": 150.404,
    "x": 4.206,
    "y": 0.5
  },
  {
    "time": 150.42,
    "x": 4.429,
    "y": 0.5
  },
  {
    "time": 150.437,
    "x": 4.648,
    "y": 0.5
  },
  {
    "time": 150.453,
    "x": 4.852,
    "y": 0.5
  },
  {
    "time": 150.469,
    "x": 5.054,
    "y": 0.5
  },
  {
    "time": 150.485,
    "x": 5.252,
    "y": 0.5
  },
  {
    "time": 150.501,
    "x": 5.437,
    "y": 0.5
  },
  {
    "time": 150.517,
    "x": 5.626,
    "y": 0.5
  },
  {
    "time": 150.533,
    "x": 5.801,
    "y": 0.5
  },
  {
    "time": 150.549,
    "x": 5.977,
    "y": 0.5
  },
  {
    "time": 150.565,
    "x": 6.145,
    "y": 0.5
  },
  {
    "time": 150.581,
    "x": 6.302,
    "y": 0.5
  },
  {
    "time": 150.597,
    "x": 6.46,
    "y": 0.5
  },
  {
    "time": 150.613,
    "x": 6.609,
    "y": 0.5
  },
  {
    "time": 150.629,
    "x": 6.75,
    "y": 0.5
  },
  {
    "time": 150.645,
    "x": 6.883,
    "y": 0.5
  },
  {
    "time": 150.661,
    "x": 7.007,
    "y": 0.5
  },
  {
    "time": 150.677,
    "x": 7.13,
    "y": 0.5
  },
  {
    "time": 150.693,
    "x": 7.241,
    "y": 0.5
  },
  {
    "time": 150.709,
    "x": 7.345,
    "y": 0.5
  },
  {
    "time": 150.725,
    "x": 7.444,
    "y": 0.5
  },
  {
    "time": 150.741,
    "x": 7.532,
    "y": 0.5
  },
  {
    "time": 150.757,
    "x": 7.615,
    "y": 0.5
  },
  {
    "time": 150.773,
    "x": 7.692,
    "y": 0.5
  },
  {
    "time": 150.789,
    "x": 7.757,
    "y": 0.5
  },
  {
    "time": 150.805,
    "x": 7.816,
    "y": 0.5
  },
  {
    "time": 150.821,
    "x": 7.867,
    "y": 0.5
  },
  {
    "time": 150.837,
    "x": 7.91,
    "y": 0.5
  },
  {
    "time": 150.853,
    "x": 7.944,
    "y": 0.5
  },
  {
    "time": 150.87,
    "x": 7.971,
    "y": 0.5
  },
  {
    "time": 150.886,
    "x": 7.989,
    "y": 0.5
  },
  {
    "time": 150.902,
    "x": 7.998,
    "y": 0.5
  },
  {
    "time": 150.918,
    "x": 7.999,
    "y": 0.5
  },
  {
    "time": 150.935,
    "x": 7.992,
    "y": 0.5
  },
  {
    "time": 150.952,
    "x": 7.976,
    "y": 0.5
  },
  {
    "time": 150.969,
    "x": 7.95,
    "y": 0.5
  },
  {
    "time": 150.985,
    "x": 7.915,
    "y": 0.5
  },
  {
    "time": 151.001,
    "x": 7.875,
    "y": 0.5
  },
  {
    "time": 151.017,
    "x": 7.825,
    "y": 0.5
  },
  {
    "time": 151.033,
    "x": 7.77,
    "y": 0.5
  },
  {
    "time": 151.049,
    "x": 7.703,
    "y": 0.5
  },
  {
    "time": 151.065,
    "x": 7.633,
    "y": 0.5
  },
  {
    "time": 151.081,
    "x": 7.552,
    "y": 0.5
  },
  {
    "time": 151.097,
    "x": 7.461,
    "y": 0.5
  },
  {
    "time": 151.113,
    "x": 7.365,
    "y": 0.5
  },
  {
    "time": 151.129,
    "x": 7.259,
    "y": 0.5
  },
  {
    "time": 151.145,
    "x": 7.147,
    "y": 0.5
  },
  {
    "time": 151.162,
    "x": 7.02,
    "y": 0.5
  },
  {
    "time": 151.179,
    "x": 6.889,
    "y": 0.5
  },
  {
    "time": 151.195,
    "x": 6.752,
    "y": 0.5
  },
  {
    "time": 151.213,
    "x": 6.601,
    "y": 0.5
  },
  {
    "time": 151.229,
    "x": 6.451,
    "y": 0.5
  },
  {
    "time": 151.245,
    "x": 6.298,
    "y": 0.5
  },
  {
    "time": 151.261,
    "x": 6.133,
    "y": 0.5
  },
  {
    "time": 151.277,
    "x": 5.965,
    "y": 0.5
  },
  {
    "time": 151.293,
    "x": 5.789,
    "y": 0.5
  },
  {
    "time": 151.308,
    "x": 5.619,
    "y": 0.5
  },
  {
    "time": 151.325,
    "x": 5.425,
    "y": 0.5
  },
  {
    "time": 151.341,
    "x": 5.234,
    "y": 0.5
  },
  {
    "time": 151.357,
    "x": 5.037,
    "y": 0.5
  },
  {
    "time": 151.373,
    "x": 4.836,
    "y": 0.5
  },
  {
    "time": 151.389,
    "x": 4.635,
    "y": 0.5
  },
  {
    "time": 151.405,
    "x": 4.425,
    "y": 0.5
  },
  {
    "time": 151.421,
    "x": 4.206,
    "y": 0.5
  },
  {
    "time": 151.437,
    "x": 3.985,
    "y": 0.5
  },
  {
    "time": 151.454,
    "x": 3.754,
    "y": 0.5
  },
  {
    "time": 151.47,
    "x": 3.513,
    "y": 0.5
  },
  {
    "time": 151.487,
    "x": 3.278,
    "y": 0.5
  },
  {
    "time": 151.503,
    "x": 3.041,
    "y": 0.5
  },
  {
    "time": 151.519,
    "x": 2.797,
    "y": 0.5
  },
  {
    "time": 151.535,
    "x": 2.565,
    "y": 0.5
  },
  {
    "time": 151.551,
    "x": 2.308,
    "y": 0.5
  },
  {
    "time": 151.569,
    "x": 2.046,
    "y": 0.5
  },
  {
    "time": 151.585,
    "x": 1.795,
    "y": 0.5
  },
  {
    "time": 151.601,
    "x": 1.539,
    "y": 0.5
  },
  {
    "time": 151.617,
    "x": 1.283,
    "y": 0.5
  },
  {
    "time": 151.633,
    "x": 1.03,
    "y": 0.5
  },
  {
    "time": 151.649,
    "x": 0.778,
    "y": 0.5
  },
  {
    "time": 151.665,
    "x": 0.523,
    "y": 0.5
  },
  {
    "time": 151.681,
    "x": 0.269,
    "y": 0.5
  },
  {
    "time": 151.697,
    "x": 0.017,
    "y": 0.5
  },
  {
    "time": 151.713,
    "x": -0.249,
    "y": 0.5
  },
  {
    "time": 151.729,
    "x": -0.505,
    "y": 0.5
  },
  {
    "time": 151.745,
    "x": -0.748,
    "y": 0.5
  },
  {
    "time": 151.761,
    "x": -1.005,
    "y": 0.5
  },
  {
    "time": 151.777,
    "x": -1.255,
    "y": 0.5
  },
  {
    "time": 151.793,
    "x": -1.518,
    "y": 0.5
  },
  {
    "time": 151.809,
    "x": -1.768,
    "y": 0.5
  },
  {
    "time": 151.826,
    "x": -2.021,
    "y": 0.5
  },
  {
    "time": 151.842,
    "x": -2.282,
    "y": 0.5
  },
  {
    "time": 151.859,
    "x": -2.542,
    "y": 0.5
  },
  {
    "time": 151.876,
    "x": -2.79,
    "y": 0.5
  },
  {
    "time": 151.892,
    "x": -3.031,
    "y": 0.5
  },
  {
    "time": 151.908,
    "x": -3.266,
    "y": 0.5
  },
  {
    "time": 151.924,
    "x": -3.494,
    "y": 0.5
  },
  {
    "time": 151.94,
    "x": -3.728,
    "y": 0.5
  },
  {
    "time": 151.956,
    "x": -3.948,
    "y": 0.5
  },
  {
    "time": 151.972,
    "x": -4.167,
    "y": 0.5
  },
  {
    "time": 151.988,
    "x": -4.382,
    "y": 0.5
  },
  {
    "time": 152.004,
    "x": -4.597,
    "y": 0.5
  },
  {
    "time": 152.02,
    "x": -4.806,
    "y": 0.5
  },
  {
    "time": 152.036,
    "x": -5.013,
    "y": 0.5
  },
  {
    "time": 152.053,
    "x": -5.214,
    "y": 0.5
  },
  {
    "time": 152.069,
    "x": -5.405,
    "y": 0.5
  },
  {
    "time": 152.085,
    "x": -5.597,
    "y": 0.5
  },
  {
    "time": 152.101,
    "x": -5.777,
    "y": 0.5
  },
  {
    "time": 152.117,
    "x": -5.949,
    "y": 0.5
  },
  {
    "time": 152.133,
    "x": -6.118,
    "y": 0.5
  },
  {
    "time": 152.149,
    "x": -6.276,
    "y": 0.5
  },
  {
    "time": 152.165,
    "x": -6.431,
    "y": 0.5
  },
  {
    "time": 152.181,
    "x": -6.586,
    "y": 0.5
  },
  {
    "time": 152.197,
    "x": -6.721,
    "y": 0.5
  },
  {
    "time": 152.214,
    "x": -6.865,
    "y": 0.5
  },
  {
    "time": 152.23,
    "x": -6.994,
    "y": 0.5
  },
  {
    "time": 152.246,
    "x": -7.114,
    "y": 0.5
  },
  {
    "time": 152.262,
    "x": -7.227,
    "y": 0.5
  },
  {
    "time": 152.278,
    "x": -7.338,
    "y": 0.5
  },
  {
    "time": 152.294,
    "x": -7.436,
    "y": 0.5
  },
  {
    "time": 152.31,
    "x": -7.524,
    "y": 0.5
  },
  {
    "time": 152.326,
    "x": -7.608,
    "y": 0.5
  },
  {
    "time": 152.342,
    "x": -7.685,
    "y": 0.5
  },
  {
    "time": 152.358,
    "x": -7.749,
    "y": 0.5
  },
  {
    "time": 152.374,
    "x": -7.809,
    "y": 0.5
  },
  {
    "time": 152.39,
    "x": -7.862,
    "y": 0.5
  },
  {
    "time": 152.406,
    "x": -7.904,
    "y": 0.5
  },
  {
    "time": 152.422,
    "x": -7.941,
    "y": 0.5
  },
  {
    "time": 152.438,
    "x": -7.967,
    "y": 0.5
  },
  {
    "time": 152.454,
    "x": -7.986,
    "y": 0.5
  },
  {
    "time": 152.47,
    "x": -7.997,
    "y": 0.5
  },
  {
    "time": 152.486,
    "x": -8.0,
    "y": 0.5
  },
  {
    "time": 152.503,
    "x": -7.994,
    "y": 0.5
  },
  {
    "time": 152.519,
    "x": -7.98,
    "y": 0.5
  },
  {
    "time": 152.535,
    "x": -7.957,
    "y": 0.5
  },
  {
    "time": 152.551,
    "x": -7.926,
    "y": 0.5
  },
  {
    "time": 152.567,
    "x": -7.887,
    "y": 0.5
  },
  {
    "time": 152.583,
    "x": -7.842,
    "y": 0.5
  },
  {
    "time": 152.6,
    "x": -7.784,
    "y": 0.5
  },
  {
    "time": 152.616,
    "x": -7.72,
    "y": 0.5
  },
  {
    "time": 152.632,
    "x": -7.649,
    "y": 0.5
  },
  {
    "time": 152.648,
    "x": -7.572,
    "y": 0.5
  },
  {
    "time": 152.664,
    "x": -7.483,
    "y": 0.5
  },
  {
    "time": 152.68,
    "x": -7.39,
    "y": 0.5
  },
  {
    "time": 152.696,
    "x": -7.289,
    "y": 0.5
  },
  {
    "time": 152.712,
    "x": -7.176,
    "y": 0.5
  },
  {
    "time": 152.729,
    "x": -7.052,
    "y": 0.5
  },
  {
    "time": 152.746,
    "x": -6.922,
    "y": 0.5
  },
  {
    "time": 152.762,
    "x": -6.787,
    "y": 0.5
  },
  {
    "time": 152.779,
    "x": -6.639,
    "y": 0.5
  },
  {
    "time": 152.795,
    "x": -6.492,
    "y": 0.5
  },
  {
    "time": 152.811,
    "x": -6.343,
    "y": 0.5
  },
  {
    "time": 152.827,
    "x": -6.182,
    "y": 0.5
  },
  {
    "time": 152.843,
    "x": -6.02,
    "y": 0.5
  },
  {
    "time": 152.859,
    "x": -5.844,
    "y": 0.5
  },
  {
    "time": 152.875,
    "x": -5.669,
    "y": 0.5
  },
  {
    "time": 152.891,
    "x": -5.479,
    "y": 0.5
  },
  {
    "time": 152.907,
    "x": -5.292,
    "y": 0.5
  },
  {
    "time": 152.923,
    "x": -5.103,
    "y": 0.5
  },
  {
    "time": 152.939,
    "x": -4.904,
    "y": 0.5
  },
  {
    "time": 152.955,
    "x": -4.689,
    "y": 0.5
  },
  {
    "time": 152.972,
    "x": -4.476,
    "y": 0.5
  },
  {
    "time": 152.988,
    "x": -4.255,
    "y": 0.5
  },
  {
    "time": 153.004,
    "x": -4.045,
    "y": 0.5
  },
  {
    "time": 153.021,
    "x": -3.804,
    "y": 0.5
  },
  {
    "time": 153.037,
    "x": -3.575,
    "y": 0.5
  },
  {
    "time": 153.053,
    "x": -3.349,
    "y": 0.5
  },
  {
    "time": 153.069,
    "x": -3.103,
    "y": 0.5
  },
  {
    "time": 153.085,
    "x": -2.879,
    "y": 0.5
  },
  {
    "time": 153.101,
    "x": -2.628,
    "y": 0.5
  },
  {
    "time": 153.117,
    "x": -2.392,
    "y": 0.5
  },
  {
    "time": 153.133,
    "x": -2.145,
    "y": 0.5
  },
  {
    "time": 153.149,
    "x": -1.893,
    "y": 0.5
  },
  {
    "time": 153.166,
    "x": -1.634,
    "y": 0.5
  },
  {
    "time": 153.182,
    "x": -1.373,
    "y": 0.5
  },
  {
    "time": 153.198,
    "x": -1.122,
    "y": 0.5
  },
  {
    "time": 153.214,
    "x": -0.876,
    "y": 0.5
  },
  {
    "time": 153.23,
    "x": -0.61,
    "y": 0.5
  },
  {
    "time": 153.247,
    "x": -0.35,
    "y": 0.5
  },
  {
    "time": 153.263,
    "x": -0.088,
    "y": 0.5
  },
  {
    "time": 153.279,
    "x": 0.166,
    "y": 0.5
  },
  {
    "time": 153.295,
    "x": 0.426,
    "y": 0.5
  },
  {
    "time": 153.311,
    "x": 0.674,
    "y": 0.5
  },
  {
    "time": 153.327,
    "x": 0.927,
    "y": 0.5
  },
  {
    "time": 153.343,
    "x": 1.18,
    "y": 0.5
  },
  {
    "time": 153.359,
    "x": 1.444,
    "y": 0.5
  },
  {
    "time": 153.375,
    "x": 1.686,
    "y": 0.5
  },
  {
    "time": 153.391,
    "x": 1.944,
    "y": 0.5
  },
  {
    "time": 153.407,
    "x": 2.187,
    "y": 0.5
  },
  {
    "time": 153.423,
    "x": 2.433,
    "y": 0.5
  },
  {
    "time": 153.439,
    "x": 2.675,
    "y": 0.5
  },
  {
    "time": 153.455,
    "x": 2.914,
    "y": 0.5
  },
  {
    "time": 153.471,
    "x": 3.155,
    "y": 0.5
  },
  {
    "time": 153.487,
    "x": 3.389,
    "y": 0.5
  },
  {
    "time": 153.503,
    "x": 3.617,
    "y": 0.5
  },
  {
    "time": 153.519,
    "x": 3.841,
    "y": 0.5
  },
  {
    "time": 153.535,
    "x": 4.062,
    "y": 0.5
  },
  {
    "time": 153.551,
    "x": 4.287,
    "y": 0.5
  },
  {
    "time": 153.567,
    "x": 4.497,
    "y": 0.5
  },
  {
    "time": 153.583,
    "x": 4.704,
    "y": 0.5
  },
  {
    "time": 153.599,
    "x": 4.916,
    "y": 0.5
  },
  {
    "time": 153.616,
    "x": 5.124,
    "y": 0.5
  },
  {
    "time": 153.632,
    "x": 5.315,
    "y": 0.5
  },
  {
    "time": 153.648,
    "x": 5.506,
    "y": 0.5
  },
  {
    "time": 153.664,
    "x": 5.685,
    "y": 0.5
  },
  {
    "time": 153.68,
    "x": 5.865,
    "y": 0.5
  },
  {
    "time": 153.696,
    "x": 6.033,
    "y": 0.5
  },
  {
    "time": 153.712,
    "x": 6.196,
    "y": 0.5
  },
  {
    "time": 153.728,
    "x": 6.358,
    "y": 0.5
  },
  {
    "time": 153.744,
    "x": 6.508,
    "y": 0.5
  },
  {
    "time": 153.76,
    "x": 6.659,
    "y": 0.5
  },
  {
    "time": 153.776,
    "x": 6.795,
    "y": 0.5
  },
  {
    "time": 153.792,
    "x": 6.924,
    "y": 0.5
  },
  {
    "time": 153.808,
    "x": 7.054,
    "y": 0.5
  },
  {
    "time": 153.824,
    "x": 7.167,
    "y": 0.5
  },
  {
    "time": 153.84,
    "x": 7.277,
    "y": 0.5
  },
  {
    "time": 153.856,
    "x": 7.384,
    "y": 0.5
  },
  {
    "time": 153.872,
    "x": 7.477,
    "y": 0.5
  },
  {
    "time": 153.888,
    "x": 7.563,
    "y": 0.5
  },
  {
    "time": 153.904,
    "x": 7.642,
    "y": 0.5
  },
  {
    "time": 153.921,
    "x": 7.717,
    "y": 0.5
  },
  {
    "time": 153.937,
    "x": 7.781,
    "y": 0.5
  },
  {
    "time": 153.953,
    "x": 7.836,
    "y": 0.5
  },
  {
    "time": 153.97,
    "x": 7.887,
    "y": 0.5
  },
  {
    "time": 153.986,
    "x": 7.926,
    "y": 0.5
  },
  {
    "time": 154.003,
    "x": 7.958,
    "y": 0.5
  },
  {
    "time": 154.019,
    "x": 7.98,
    "y": 0.5
  },
  {
    "time": 154.035,
    "x": 7.994,
    "y": 0.5
  },
  {
    "time": 154.051,
    "x": 8.0,
    "y": 0.5
  },
  {
    "time": 154.067,
    "x": 7.997,
    "y": 0.5
  },
  {
    "time": 154.083,
    "x": 7.986,
    "y": 0.5
  },
  {
    "time": 154.1,
    "x": 7.967,
    "y": 0.5
  },
  {
    "time": 154.117,
    "x": 7.937,
    "y": 0.5
  },
  {
    "time": 154.134,
    "x": 7.899,
    "y": 0.5
  },
  {
    "time": 154.15,
    "x": 7.854,
    "y": 0.5
  },
  {
    "time": 154.167,
    "x": 7.798,
    "y": 0.5
  },
  {
    "time": 154.183,
    "x": 7.736,
    "y": 0.5
  },
  {
    "time": 154.199,
    "x": 7.666,
    "y": 0.5
  },
  {
    "time": 154.216,
    "x": 7.586,
    "y": 0.5
  },
  {
    "time": 154.232,
    "x": 7.496,
    "y": 0.5
  },
  {
    "time": 154.248,
    "x": 7.404,
    "y": 0.5
  },
  {
    "time": 154.264,
    "x": 7.303,
    "y": 0.5
  },
  {
    "time": 154.28,
    "x": 7.196,
    "y": 0.5
  },
  {
    "time": 154.296,
    "x": 7.08,
    "y": 0.5
  },
  {
    "time": 154.312,
    "x": 6.956,
    "y": 0.5
  },
  {
    "time": 154.329,
    "x": 6.823,
    "y": 0.5
  },
  {
    "time": 154.345,
    "x": 6.684,
    "y": 0.5
  },
  {
    "time": 154.361,
    "x": 6.537,
    "y": 0.5
  },
  {
    "time": 154.377,
    "x": 6.383,
    "y": 0.5
  },
  {
    "time": 154.394,
    "x": 6.224,
    "y": 0.5
  },
  {
    "time": 154.41,
    "x": 6.053,
    "y": 0.5
  },
  {
    "time": 154.426,
    "x": 5.883,
    "y": 0.5
  },
  {
    "time": 154.442,
    "x": 5.711,
    "y": 0.5
  },
  {
    "time": 154.458,
    "x": 5.522,
    "y": 0.5
  },
  {
    "time": 154.474,
    "x": 5.337,
    "y": 0.5
  },
  {
    "time": 154.49,
    "x": 5.149,
    "y": 0.5
  },
  {
    "time": 154.506,
    "x": 4.951,
    "y": 0.5
  },
  {
    "time": 154.522,
    "x": 4.74,
    "y": 0.5
  },
  {
    "time": 154.538,
    "x": 4.537,
    "y": 0.5
  },
  {
    "time": 154.554,
    "x": 4.321,
    "y": 0.5
  },
  {
    "time": 154.571,
    "x": 4.096,
    "y": 0.5
  },
  {
    "time": 154.587,
    "x": 3.869,
    "y": 0.5
  },
  {
    "time": 154.603,
    "x": 3.647,
    "y": 0.5
  },
  {
    "time": 154.619,
    "x": 3.412,
    "y": 0.5
  },
  {
    "time": 154.636,
    "x": 3.17,
    "y": 0.5
  },
  {
    "time": 154.652,
    "x": 2.93,
    "y": 0.5
  },
  {
    "time": 154.667,
    "x": 2.701,
    "y": 0.5
  },
  {
    "time": 154.684,
    "x": 2.452,
    "y": 0.5
  },
  {
    "time": 154.701,
    "x": 2.192,
    "y": 0.5
  },
  {
    "time": 154.717,
    "x": 1.934,
    "y": 0.5
  },
  {
    "time": 154.733,
    "x": 1.686,
    "y": 0.5
  },
  {
    "time": 154.749,
    "x": 1.436,
    "y": 0.5
  },
  {
    "time": 154.765,
    "x": 1.191,
    "y": 0.5
  },
  {
    "time": 154.781,
    "x": 0.931,
    "y": 0.5
  },
  {
    "time": 154.798,
    "x": 0.667,
    "y": 0.5
  },
  {
    "time": 154.814,
    "x": 0.398,
    "y": 0.5
  },
  {
    "time": 154.831,
    "x": 0.137,
    "y": 0.5
  },
  {
    "time": 154.848,
    "x": -0.13,
    "y": 0.5
  },
  {
    "time": 154.863,
    "x": -0.385,
    "y": 0.5
  },
  {
    "time": 154.879,
    "x": -0.633,
    "y": 0.5
  },
  {
    "time": 154.896,
    "x": -0.898,
    "y": 0.5
  },
  {
    "time": 154.912,
    "x": -1.161,
    "y": 0.5
  },
  {
    "time": 154.928,
    "x": -1.41,
    "y": 0.5
  },
  {
    "time": 154.944,
    "x": -1.656,
    "y": 0.5
  },
  {
    "time": 154.961,
    "x": -1.92,
    "y": 0.5
  },
  {
    "time": 154.978,
    "x": -2.184,
    "y": 0.5
  },
  {
    "time": 154.995,
    "x": -2.443,
    "y": 0.5
  },
  {
    "time": 155.012,
    "x": -2.702,
    "y": 0.5
  },
  {
    "time": 155.029,
    "x": -2.957,
    "y": 0.5
  },
  {
    "time": 155.045,
    "x": -3.194,
    "y": 0.5
  },
  {
    "time": 155.062,
    "x": -3.439,
    "y": 0.5
  },
  {
    "time": 155.078,
    "x": -3.679,
    "y": 0.5
  },
  {
    "time": 155.095,
    "x": -3.909,
    "y": 0.5
  },
  {
    "time": 155.111,
    "x": -4.132,
    "y": 0.5
  },
  {
    "time": 155.127,
    "x": -4.355,
    "y": 0.5
  },
  {
    "time": 155.143,
    "x": -4.566,
    "y": 0.5
  },
  {
    "time": 155.159,
    "x": -4.77,
    "y": 0.5
  },
  {
    "time": 155.175,
    "x": -4.972,
    "y": 0.5
  },
  {
    "time": 155.191,
    "x": -5.179,
    "y": 0.5
  },
  {
    "time": 155.207,
    "x": -5.368,
    "y": 0.5
  },
  {
    "time": 155.223,
    "x": -5.55,
    "y": 0.5
  },
  {
    "time": 155.239,
    "x": -5.739,
    "y": 0.5
  },
  {
    "time": 155.255,
    "x": -5.911,
    "y": 0.5
  },
  {
    "time": 155.272,
    "x": -6.085,
    "y": 0.5
  },
  {
    "time": 155.288,
    "x": -6.251,
    "y": 0.5
  },
  {
    "time": 155.304,
    "x": -6.41,
    "y": 0.5
  },
  {
    "time": 155.321,
    "x": -6.564,
    "y": 0.5
  },
  {
    "time": 155.337,
    "x": -6.71,
    "y": 0.5
  },
  {
    "time": 155.354,
    "x": -6.851,
    "y": 0.5
  },
  {
    "time": 155.37,
    "x": -6.982,
    "y": 0.5
  },
  {
    "time": 155.386,
    "x": -7.105,
    "y": 0.5
  },
  {
    "time": 155.402,
    "x": -7.217,
    "y": 0.5
  },
  {
    "time": 155.418,
    "x": -7.329,
    "y": 0.5
  },
  {
    "time": 155.435,
    "x": -7.428,
    "y": 0.5
  },
  {
    "time": 155.45,
    "x": -7.518,
    "y": 0.5
  },
  {
    "time": 155.466,
    "x": -7.601,
    "y": 0.5
  },
  {
    "time": 155.482,
    "x": -7.676,
    "y": 0.5
  },
  {
    "time": 155.499,
    "x": -7.747,
    "y": 0.5
  },
  {
    "time": 155.515,
    "x": -7.808,
    "y": 0.5
  },
  {
    "time": 155.531,
    "x": -7.859,
    "y": 0.5
  },
  {
    "time": 155.548,
    "x": -7.905,
    "y": 0.5
  },
  {
    "time": 155.564,
    "x": -7.941,
    "y": 0.5
  },
  {
    "time": 155.58,
    "x": -7.968,
    "y": 0.5
  },
  {
    "time": 155.597,
    "x": -7.987,
    "y": 0.5
  },
  {
    "time": 155.613,
    "x": -7.998,
    "y": 0.5
  },
  {
    "time": 155.629,
    "x": -8.0,
    "y": 0.5
  },
  {
    "time": 155.646,
    "x": -7.993,
    "y": 0.5
  },
  {
    "time": 155.662,
    "x": -7.977,
    "y": 0.5
  },
  {
    "time": 155.678,
    "x": -7.954,
    "y": 0.5
  },
  {
    "time": 155.694,
    "x": -7.924,
    "y": 0.5
  },
  {
    "time": 155.711,
    "x": -7.883,
    "y": 0.5
  },
  {
    "time": 155.727,
    "x": -7.832,
    "y": 0.5
  },
  {
    "time": 155.743,
    "x": -7.778,
    "y": 0.5
  },
  {
    "time": 155.759,
    "x": -7.712,
    "y": 0.5
  },
  {
    "time": 155.775,
    "x": -7.643,
    "y": 0.5
  },
  {
    "time": 155.791,
    "x": -7.563,
    "y": 0.5
  },
  {
    "time": 155.807,
    "x": -7.476,
    "y": 0.5
  },
  {
    "time": 155.823,
    "x": -7.381,
    "y": 0.5
  },
  {
    "time": 155.839,
    "x": -7.277,
    "y": 0.5
  },
  {
    "time": 155.855,
    "x": -7.166,
    "y": 0.5
  },
  {
    "time": 155.871,
    "x": -7.048,
    "y": 0.5
  },
  {
    "time": 155.887,
    "x": -6.923,
    "y": 0.5
  },
  {
    "time": 155.903,
    "x": -6.79,
    "y": 0.5
  },
  {
    "time": 155.919,
    "x": -6.655,
    "y": 0.5
  },
  {
    "time": 155.935,
    "x": -6.506,
    "y": 0.5
  },
  {
    "time": 155.951,
    "x": -6.359,
    "y": 0.5
  },
  {
    "time": 155.967,
    "x": -6.196,
    "y": 0.5
  },
  {
    "time": 155.983,
    "x": -6.035,
    "y": 0.5
  },
  {
    "time": 155.999,
    "x": -5.863,
    "y": 0.5
  },
  {
    "time": 156.016,
    "x": -5.677,
    "y": 0.5
  },
  {
    "time": 156.033,
    "x": -5.484,
    "y": 0.5
  },
  {
    "time": 156.049,
    "x": -5.293,
    "y": 0.5
  },
  {
    "time": 156.065,
    "x": -5.093,
    "y": 0.5
  },
  {
    "time": 156.081,
    "x": -4.892,
    "y": 0.5
  },
  {
    "time": 156.098,
    "x": -4.681,
    "y": 0.5
  },
  {
    "time": 156.114,
    "x": -4.468,
    "y": 0.5
  },
  {
    "time": 156.131,
    "x": -4.243,
    "y": 0.5
  },
  {
    "time": 156.147,
    "x": -4.013,
    "y": 0.5
  },
  {
    "time": 156.163,
    "x": -3.798,
    "y": 0.5
  },
  {
    "time": 156.18,
    "x": -3.558,
    "y": 0.5
  },
  {
    "time": 156.196,
    "x": -3.321,
    "y": 0.5
  },
  {
    "time": 156.213,
    "x": -3.081,
    "y": 0.5
  },
  {
    "time": 156.229,
    "x": -2.838,
    "y": 0.5
  },
  {
    "time": 156.245,
    "x": -2.595,
    "y": 0.5
  },
  {
    "time": 156.261,
    "x": -2.345,
    "y": 0.5
  },
  {
    "time": 156.277,
    "x": -2.11,
    "y": 0.5
  },
  {
    "time": 156.293,
    "x": -1.857,
    "y": 0.5
  },
  {
    "time": 156.309,
    "x": -1.605,
    "y": 0.5
  },
  {
    "time": 156.325,
    "x": -1.362,
    "y": 0.5
  },
  {
    "time": 156.341,
    "x": -1.107,
    "y": 0.5
  },
  {
    "time": 156.357,
    "x": -0.85,
    "y": 0.5
  },
  {
    "time": 156.373,
    "x": -0.599,
    "y": 0.5
  },
  {
    "time": 156.39,
    "x": -0.331,
    "y": 0.5
  },
  {
    "time": 156.405,
    "x": -0.08,
    "y": 0.5
  },
  {
    "time": 156.421,
    "x": 0.177,
    "y": 0.5
  },
  {
    "time": 156.437,
    "x": 0.431,
    "y": 0.5
  },
  {
    "time": 156.453,
    "x": 0.682,
    "y": 0.5
  },
  {
    "time": 156.469,
    "x": 0.935,
    "y": 0.5
  },
  {
    "time": 156.485,
    "x": 1.19,
    "y": 0.5
  },
  {
    "time": 156.501,
    "x": 1.447,
    "y": 0.5
  },
  {
    "time": 156.517,
    "x": 1.691,
    "y": 0.5
  },
  {
    "time": 156.533,
    "x": 1.952,
    "y": 0.5
  },
  {
    "time": 156.549,
    "x": 2.196,
    "y": 0.5
  },
  {
    "time": 156.565,
    "x": 2.441,
    "y": 0.5
  },
  {
    "time": 156.582,
    "x": 2.69,
    "y": 0.5
  },
  {
    "time": 156.598,
    "x": 2.934,
    "y": 0.5
  },
  {
    "time": 156.614,
    "x": 3.176,
    "y": 0.5
  },
  {
    "time": 156.63,
    "x": 3.403,
    "y": 0.5
  },
  {
    "time": 156.646,
    "x": 3.639,
    "y": 0.5
  },
  {
    "time": 156.662,
    "x": 3.858,
    "y": 0.5
  },
  {
    "time": 156.679,
    "x": 4.092,
    "y": 0.5
  },
  {
    "time": 156.695,
    "x": 4.315,
    "y": 0.5
  },
  {
    "time": 156.711,
    "x": 4.527,
    "y": 0.5
  },
  {
    "time": 156.727,
    "x": 4.734,
    "y": 0.5
  },
  {
    "time": 156.744,
    "x": 4.949,
    "y": 0.5
  },
  {
    "time": 156.761,
    "x": 5.158,
    "y": 0.5
  },
  {
    "time": 156.777,
    "x": 5.36,
    "y": 0.5
  },
  {
    "time": 156.793,
    "x": 5.543,
    "y": 0.5
  },
  {
    "time": 156.809,
    "x": 5.727,
    "y": 0.5
  },
  {
    "time": 156.826,
    "x": 5.908,
    "y": 0.5
  },
  {
    "time": 156.842,
    "x": 6.078,
    "y": 0.5
  },
  {
    "time": 156.858,
    "x": 6.25,
    "y": 0.5
  },
  {
    "time": 156.874,
    "x": 6.402,
    "y": 0.5
  },
  {
    "time": 156.89,
    "x": 6.554,
    "y": 0.5
  },
  {
    "time": 156.906,
    "x": 6.692,
    "y": 0.5
  },
  {
    "time": 156.923,
    "x": 6.837,
    "y": 0.5
  },
  {
    "time": 156.939,
    "x": 6.971,
    "y": 0.5
  },
  {
    "time": 156.956,
    "x": 7.096,
    "y": 0.5
  },
  {
    "time": 156.972,
    "x": 7.216,
    "y": 0.5
  },
  {
    "time": 156.989,
    "x": 7.324,
    "y": 0.5
  },
  {
    "time": 157.005,
    "x": 7.424,
    "y": 0.5
  },
  {
    "time": 157.022,
    "x": 7.522,
    "y": 0.5
  },
  {
    "time": 157.038,
    "x": 7.605,
    "y": 0.5
  },
  {
    "time": 157.055,
    "x": 7.684,
    "y": 0.5
  },
  {
    "time": 157.07,
    "x": 7.75,
    "y": 0.5
  },
  {
    "time": 157.086,
    "x": 7.81,
    "y": 0.5
  },
  {
    "time": 157.103,
    "x": 7.862,
    "y": 0.5
  },
  {
    "time": 157.119,
    "x": 7.907,
    "y": 0.5
  },
  {
    "time": 157.136,
    "x": 7.942,
    "y": 0.5
  },
  {
    "time": 157.151,
    "x": 7.968,
    "y": 0.5
  },
  {
    "time": 157.168,
    "x": 7.987,
    "y": 0.5
  },
  {
    "time": 157.183,
    "x": 7.998,
    "y": 0.5
  },
  {
    "time": 157.2,
    "x": 8.0,
    "y": 0.5
  },
  {
    "time": 157.216,
    "x": 7.993,
    "y": 0.5
  },
  {
    "time": 157.232,
    "x": 7.979,
    "y": 0.5
  },
  {
    "time": 157.248,
    "x": 7.956,
    "y": 0.5
  },
  {
    "time": 157.264,
    "x": 7.924,
    "y": 0.5
  },
  {
    "time": 157.28,
    "x": 7.886,
    "y": 0.5
  },
  {
    "time": 157.296,
    "x": 7.839,
    "y": 0.5
  },
  {
    "time": 157.312,
    "x": 7.784,
    "y": 0.5
  },
  {
    "time": 157.328,
    "x": 7.721,
    "y": 0.5
  },
  {
    "time": 157.345,
    "x": 7.647,
    "y": 0.5
  },
  {
    "time": 157.361,
    "x": 7.566,
    "y": 0.5
  },
  {
    "time": 157.377,
    "x": 7.48,
    "y": 0.5
  },
  {
    "time": 157.393,
    "x": 7.385,
    "y": 0.5
  },
  {
    "time": 157.41,
    "x": 7.278,
    "y": 0.5
  },
  {
    "time": 157.426,
    "x": 7.168,
    "y": 0.5
  },
  {
    "time": 157.442,
    "x": 7.051,
    "y": 0.5
  },
  {
    "time": 157.458,
    "x": 6.921,
    "y": 0.5
  },
  {
    "time": 157.474,
    "x": 6.787,
    "y": 0.5
  },
  {
    "time": 157.49,
    "x": 6.651,
    "y": 0.5
  },
  {
    "time": 157.507,
    "x": 6.501,
    "y": 0.5
  },
  {
    "time": 157.524,
    "x": 6.339,
    "y": 0.5
  },
  {
    "time": 157.54,
    "x": 6.176,
    "y": 0.5
  },
  {
    "time": 157.556,
    "x": 6.008,
    "y": 0.5
  },
  {
    "time": 157.572,
    "x": 5.841,
    "y": 0.5
  },
  {
    "time": 157.588,
    "x": 5.664,
    "y": 0.5
  },
  {
    "time": 157.605,
    "x": 5.47,
    "y": 0.5
  },
  {
    "time": 157.62,
    "x": 5.288,
    "y": 0.5
  },
  {
    "time": 157.636,
    "x": 5.088,
    "y": 0.5
  },
  {
    "time": 157.652,
    "x": 4.888,
    "y": 0.5
  },
  {
    "time": 157.668,
    "x": 4.692,
    "y": 0.5
  },
  {
    "time": 157.684,
    "x": 4.48,
    "y": 0.5
  },
  {
    "time": 157.701,
    "x": 4.254,
    "y": 0.5
  },
  {
    "time": 157.717,
    "x": 4.032,
    "y": 0.5
  },
  {
    "time": 157.733,
    "x": 3.807,
    "y": 0.5
  },
  {
    "time": 157.749,
    "x": 3.576,
    "y": 0.5
  },
  {
    "time": 157.765,
    "x": 3.351,
    "y": 0.5
  },
  {
    "time": 157.781,
    "x": 3.11,
    "y": 0.5
  },
  {
    "time": 157.798,
    "x": 2.869,
    "y": 0.5
  },
  {
    "time": 157.813,
    "x": 2.631,
    "y": 0.5
  },
  {
    "time": 157.829,
    "x": 2.391,
    "y": 0.5
  },
  {
    "time": 157.845,
    "x": 2.153,
    "y": 0.5
  },
  {
    "time": 157.861,
    "x": 1.903,
    "y": 0.5
  },
  {
    "time": 157.878,
    "x": 1.641,
    "y": 0.5
  },
  {
    "time": 157.894,
    "x": 1.384,
    "y": 0.5
  },
  {
    "time": 157.911,
    "x": 1.123,
    "y": 0.5
  },
  {
    "time": 157.926,
    "x": 0.883,
    "y": 0.5
  },
  {
    "time": 157.942,
    "x": 0.627,
    "y": 0.5
  },
  {
    "time": 157.959,
    "x": 0.358,
    "y": 0.5
  },
  {
    "time": 157.975,
    "x": 0.098,
    "y": 0.5
  },
  {
    "time": 157.991,
    "x": -0.159,
    "y": 0.5
  },
  {
    "time": 158.007,
    "x": -0.416,
    "y": 0.5
  },
  {
    "time": 158.024,
    "x": -0.685,
    "y": 0.5
  },
  {
    "time": 158.04,
    "x": -0.939,
    "y": 0.5
  },
  {
    "time": 158.056,
    "x": -1.203,
    "y": 0.5
  },
  {
    "time": 158.072,
    "x": -1.451,
    "y": 0.5
  },
  {
    "time": 158.089,
    "x": -1.709,
    "y": 0.5
  },
  {
    "time": 158.106,
    "x": -1.974,
    "y": 0.5
  },
  {
    "time": 158.122,
    "x": -2.231,
    "y": 0.5
  },
  {
    "time": 158.138,
    "x": -2.473,
    "y": 0.5
  },
  {
    "time": 158.155,
    "x": -2.721,
    "y": 0.5
  },
  {
    "time": 158.17,
    "x": -2.955,
    "y": 0.5
  },
  {
    "time": 158.186,
    "x": -3.19,
    "y": 0.5
  },
  {
    "time": 158.203,
    "x": -3.432,
    "y": 0.5
  },
  {
    "time": 158.219,
    "x": -3.662,
    "y": 0.5
  },
  {
    "time": 158.235,
    "x": -3.897,
    "y": 0.5
  },
  {
    "time": 158.251,
    "x": -4.112,
    "y": 0.5
  },
  {
    "time": 158.267,
    "x": -4.333,
    "y": 0.5
  },
  {
    "time": 158.283,
    "x": -4.543,
    "y": 0.5
  },
  {
    "time": 158.3,
    "x": -4.76,
    "y": 0.5
  },
  {
    "time": 158.315,
    "x": -4.962,
    "y": 0.5
  },
  {
    "time": 158.331,
    "x": -5.155,
    "y": 0.5
  },
  {
    "time": 158.347,
    "x": -5.344,
    "y": 0.5
  },
  {
    "time": 158.363,
    "x": -5.533,
    "y": 0.5
  },
  {
    "time": 158.379,
    "x": -5.72,
    "y": 0.5
  },
  {
    "time": 158.396,
    "x": -5.901,
    "y": 0.5
  },
  {
    "time": 158.412,
    "x": -6.071,
    "y": 0.5
  },
  {
    "time": 158.428,
    "x": -6.234,
    "y": 0.5
  },
  {
    "time": 158.444,
    "x": -6.396,
    "y": 0.5
  },
  {
    "time": 158.461,
    "x": -6.551,
    "y": 0.5
  },
  {
    "time": 158.477,
    "x": -6.7,
    "y": 0.5
  },
  {
    "time": 158.494,
    "x": -6.839,
    "y": 0.5
  },
  {
    "time": 158.511,
    "x": -6.977,
    "y": 0.5
  },
  {
    "time": 158.527,
    "x": -7.101,
    "y": 0.5
  },
  {
    "time": 158.544,
    "x": -7.219,
    "y": 0.5
  },
  {
    "time": 158.559,
    "x": -7.323,
    "y": 0.5
  },
  {
    "time": 158.575,
    "x": -7.42,
    "y": 0.5
  },
  {
    "time": 158.591,
    "x": -7.513,
    "y": 0.5
  },
  {
    "time": 158.607,
    "x": -7.598,
    "y": 0.5
  },
  {
    "time": 158.623,
    "x": -7.673,
    "y": 0.5
  },
  {
    "time": 158.639,
    "x": -7.742,
    "y": 0.5
  },
  {
    "time": 158.655,
    "x": -7.804,
    "y": 0.5
  },
  {
    "time": 158.67,
    "x": -7.853,
    "y": 0.5
  },
  {
    "time": 158.687,
    "x": -7.898,
    "y": 0.5
  },
  {
    "time": 158.702,
    "x": -7.934,
    "y": 0.5
  },
  {
    "time": 158.719,
    "x": -7.964,
    "y": 0.5
  },
  {
    "time": 158.735,
    "x": -7.984,
    "y": 0.5
  },
  {
    "time": 158.752,
    "x": -7.997,
    "y": 0.5
  },
  {
    "time": 158.768,
    "x": -8.0,
    "y": 0.5
  },
  {
    "time": 158.784,
    "x": -7.995,
    "y": 0.5
  },
  {
    "time": 158.8,
    "x": -7.982,
    "y": 0.5
  },
  {
    "time": 158.817,
    "x": -7.96,
    "y": 0.5
  },
  {
    "time": 158.833,
    "x": -7.929,
    "y": 0.5
  },
  {
    "time": 158.85,
    "x": -7.889,
    "y": 0.5
  },
  {
    "time": 158.865,
    "x": -7.844,
    "y": 0.5
  },
  {
    "time": 158.882,
    "x": -7.788,
    "y": 0.5
  },
  {
    "time": 158.898,
    "x": -7.724,
    "y": 0.5
  },
  {
    "time": 158.915,
    "x": -7.651,
    "y": 0.5
  },
  {
    "time": 158.93,
    "x": -7.574,
    "y": 0.5
  },
  {
    "time": 158.947,
    "x": -7.485,
    "y": 0.5
  },
  {
    "time": 158.963,
    "x": -7.389,
    "y": 0.5
  },
  {
    "time": 158.98,
    "x": -7.282,
    "y": 0.5
  },
  {
    "time": 158.996,
    "x": -7.171,
    "y": 0.5
  },
  {
    "time": 159.012,
    "x": -7.053,
    "y": 0.5
  },
  {
    "time": 159.029,
    "x": -6.922,
    "y": 0.5
  },
  {
    "time": 159.045,
    "x": -6.787,
    "y": 0.5
  },
  {
    "time": 159.062,
    "x": -6.646,
    "y": 0.5
  },
  {
    "time": 159.077,
    "x": -6.503,
    "y": 0.5
  },
  {
    "time": 159.093,
    "x": -6.348,
    "y": 0.5
  },
  {
    "time": 159.11,
    "x": -6.186,
    "y": 0.5
  },
  {
    "time": 159.126,
    "x": -6.014,
    "y": 0.5
  },
  {
    "time": 159.142,
    "x": -5.843,
    "y": 0.5
  },
  {
    "time": 159.158,
    "x": -5.664,
    "y": 0.5
  },
  {
    "time": 159.174,
    "x": -5.487,
    "y": 0.5
  },
  {
    "time": 159.191,
    "x": -5.287,
    "y": 0.5
  },
  {
    "time": 159.207,
    "x": -5.09,
    "y": 0.5
  },
  {
    "time": 159.223,
    "x": -4.889,
    "y": 0.5
  },
  {
    "time": 159.239,
    "x": -4.681,
    "y": 0.5
  },
  {
    "time": 159.255,
    "x": -4.474,
    "y": 0.5
  },
  {
    "time": 159.271,
    "x": -4.258,
    "y": 0.5
  },
  {
    "time": 159.287,
    "x": -4.041,
    "y": 0.5
  },
  {
    "time": 159.303,
    "x": -3.814,
    "y": 0.5
  },
  {
    "time": 159.319,
    "x": -3.59,
    "y": 0.5
  },
  {
    "time": 159.335,
    "x": -3.361,
    "y": 0.5
  },
  {
    "time": 159.351,
    "x": -3.128,
    "y": 0.5
  },
  {
    "time": 159.367,
    "x": -2.883,
    "y": 0.5
  },
  {
    "time": 159.383,
    "x": -2.651,
    "y": 0.5
  },
  {
    "time": 159.4,
    "x": -2.396,
    "y": 0.5
  },
  {
    "time": 159.416,
    "x": -2.146,
    "y": 0.5
  },
  {
    "time": 159.432,
    "x": -1.9,
    "y": 0.5
  },
  {
    "time": 159.448,
    "x": -1.65,
    "y": 0.5
  },
  {
    "time": 159.464,
    "x": -1.392,
    "y": 0.5
  },
  {
    "time": 159.48,
    "x": -1.143,
    "y": 0.5
  },
  {
    "time": 159.496,
    "x": -0.887,
    "y": 0.5
  },
  {
    "time": 159.512,
    "x": -0.635,
    "y": 0.5
  },
  {
    "time": 159.529,
    "x": -0.369,
    "y": 0.5
  },
  {
    "time": 159.545,
    "x": -0.108,
    "y": 0.5
  },
  {
    "time": 159.562,
    "x": 0.159,
    "y": 0.5
  },
  {
    "time": 159.578,
    "x": 0.419,
    "y": 0.5
  },
  {
    "time": 159.594,
    "x": 0.676,
    "y": 0.5
  },
  {
    "time": 159.61,
    "x": 0.936,
    "y": 0.5
  },
  {
    "time": 159.626,
    "x": 1.181,
    "y": 0.5
  },
  {
    "time": 159.642,
    "x": 1.431,
    "y": 0.5
  },
  {
    "time": 159.658,
    "x": 1.691,
    "y": 0.5
  },
  {
    "time": 159.674,
    "x": 1.937,
    "y": 0.5
  },
  {
    "time": 159.69,
    "x": 2.186,
    "y": 0.5
  },
  {
    "time": 159.706,
    "x": 2.425,
    "y": 0.5
  },
  {
    "time": 159.722,
    "x": 2.674,
    "y": 0.5
  },
  {
    "time": 159.739,
    "x": 2.923,
    "y": 0.5
  },
  {
    "time": 159.756,
    "x": 3.172,
    "y": 0.5
  },
  {
    "time": 159.771,
    "x": 3.393,
    "y": 0.5
  },
  {
    "time": 159.788,
    "x": 3.634,
    "y": 0.5
  },
  {
    "time": 159.803,
    "x": 3.849,
    "y": 0.5
  },
  {
    "time": 159.819,
    "x": 4.072,
    "y": 0.5
  },
  {
    "time": 159.836,
    "x": 4.304,
    "y": 0.5
  },
  {
    "time": 159.852,
    "x": 4.526,
    "y": 0.5
  },
  {
    "time": 159.868,
    "x": 4.733,
    "y": 0.5
  },
  {
    "time": 159.884,
    "x": 4.935,
    "y": 0.5
  },
  {
    "time": 159.901,
    "x": 5.138,
    "y": 0.5
  },
  {
    "time": 159.917,
    "x": 5.334,
    "y": 0.5
  },
  {
    "time": 159.933,
    "x": 5.526,
    "y": 0.5
  },
  {
    "time": 159.949,
    "x": 5.71,
    "y": 0.5
  },
  {
    "time": 159.965,
    "x": 5.884,
    "y": 0.5
  },
  {
    "time": 159.982,
    "x": 6.063,
    "y": 0.5
  },
  {
    "time": 159.999,
    "x": 6.234,
    "y": 0.5
  },
  {
    "time": 160.014,
    "x": 6.386,
    "y": 0.5
  },
  {
    "time": 160.031,
    "x": 6.542,
    "y": 0.5
  },
  {
    "time": 160.047,
    "x": 6.688,
    "y": 0.5
  },
  {
    "time": 160.063,
    "x": 6.831,
    "y": 0.5
  },
  {
    "time": 160.079,
    "x": 6.957,
    "y": 0.5
  },
  {
    "time": 160.095,
    "x": 7.082,
    "y": 0.5
  },
  {
    "time": 160.112,
    "x": 7.201,
    "y": 0.5
  },
  {
    "time": 160.129,
    "x": 7.316,
    "y": 0.5
  },
  {
    "time": 160.146,
    "x": 7.421,
    "y": 0.5
  },
  {
    "time": 160.163,
    "x": 7.517,
    "y": 0.5
  },
  {
    "time": 160.179,
    "x": 7.601,
    "y": 0.5
  },
  {
    "time": 160.194,
    "x": 7.674,
    "y": 0.5
  },
  {
    "time": 160.21,
    "x": 7.742,
    "y": 0.5
  },
  {
    "time": 160.226,
    "x": 7.804,
    "y": 0.5
  },
  {
    "time": 160.242,
    "x": 7.856,
    "y": 0.5
  },
  {
    "time": 160.258,
    "x": 7.9,
    "y": 0.5
  },
  {
    "time": 160.274,
    "x": 7.936,
    "y": 0.5
  },
  {
    "time": 160.29,
    "x": 7.964,
    "y": 0.5
  },
  {
    "time": 160.306,
    "x": 7.985,
    "y": 0.5
  },
  {
    "time": 160.322,
    "x": 7.996,
    "y": 0.5
  },
  {
    "time": 160.338,
    "x": 8.0,
    "y": 0.5
  },
  {
    "time": 160.354,
    "x": 7.995,
    "y": 0.5
  },
  {
    "time": 160.37,
    "x": 7.983,
    "y": 0.5
  },
  {
    "time": 160.386,
    "x": 7.962,
    "y": 0.5
  },
  {
    "time": 160.403,
    "x": 7.932,
    "y": 0.5
  },
  {
    "time": 160.418,
    "x": 7.895,
    "y": 0.5
  },
  {
    "time": 160.435,
    "x": 7.848,
    "y": 0.5
  },
  {
    "time": 160.451,
    "x": 7.792,
    "y": 0.5
  },
  {
    "time": 160.467,
    "x": 7.733,
    "y": 0.5
  },
  {
    "time": 160.483,
    "x": 7.662,
    "y": 0.5
  },
  {
    "time": 160.499,
    "x": 7.584,
    "y": 0.5
  },
  {
    "time": 160.516,
    "x": 7.495,
    "y": 0.5
  },
  {
    "time": 160.533,
    "x": 7.396,
    "y": 0.5
  },
  {
    "time": 160.549,
    "x": 7.29,
    "y": 0.5
  },
  {
    "time": 160.566,
    "x": 7.179,
    "y": 0.5
  },
  {
    "time": 160.581,
    "x": 7.068,
    "y": 0.5
  },
  {
    "time": 160.597,
    "x": 6.945,
    "y": 0.5
  },
  {
    "time": 160.614,
    "x": 6.807,
    "y": 0.5
  },
  {
    "time": 160.631,
    "x": 6.66,
    "y": 0.5
  },
  {
    "time": 160.648,
    "x": 6.507,
    "y": 0.5
  },
  {
    "time": 160.664,
    "x": 6.355,
    "y": 0.5
  },
  {
    "time": 160.679,
    "x": 6.198,
    "y": 0.5
  },
  {
    "time": 160.695,
    "x": 6.038,
    "y": 0.5
  },
  {
    "time": 160.711,
    "x": 5.862,
    "y": 0.5
  },
  {
    "time": 160.728,
    "x": 5.683,
    "y": 0.5
  },
  {
    "time": 160.743,
    "x": 5.507,
    "y": 0.5
  },
  {
    "time": 160.759,
    "x": 5.316,
    "y": 0.5
  },
  {
    "time": 160.775,
    "x": 5.127,
    "y": 0.5
  },
  {
    "time": 160.791,
    "x": 4.926,
    "y": 0.5
  },
  {
    "time": 160.807,
    "x": 4.714,
    "y": 0.5
  },
  {
    "time": 160.823,
    "x": 4.509,
    "y": 0.5
  },
  {
    "time": 160.84,
    "x": 4.288,
    "y": 0.5
  },
  {
    "time": 160.856,
    "x": 4.063,
    "y": 0.5
  },
  {
    "time": 160.873,
    "x": 3.834,
    "y": 0.5
  },
  {
    "time": 160.89,
    "x": 3.59,
    "y": 0.5
  },
  {
    "time": 160.906,
    "x": 3.351,
    "y": 0.5
  },
  {
    "time": 160.922,
    "x": 3.124,
    "y": 0.5
  },
  {
    "time": 160.938,
    "x": 2.882,
    "y": 0.5
  },
  {
    "time": 160.954,
    "x": 2.64,
    "y": 0.5
  },
  {
    "time": 160.97,
    "x": 2.398,
    "y": 0.5
  },
  {
    "time": 160.986,
    "x": 2.157,
    "y": 0.5
  },
  {
    "time": 161.002,
    "x": 1.913,
    "y": 0.5
  },
  {
    "time": 161.019,
    "x": 1.651,
    "y": 0.5
  },
  {
    "time": 161.035,
    "x": 1.401,
    "y": 0.5
  },
  {
    "time": 161.05,
    "x": 1.155,
    "y": 0.5
  },
  {
    "time": 161.066,
    "x": 0.897,
    "y": 0.5
  },
  {
    "time": 161.083,
    "x": 0.639,
    "y": 0.5
  },
  {
    "time": 161.099,
    "x": 0.383,
    "y": 0.5
  },
  {
    "time": 161.114,
    "x": 0.132,
    "y": 0.5
  },
  {
    "time": 161.13,
    "x": -0.117,
    "y": 0.5
  },
  {
    "time": 161.146,
    "x": -0.377,
    "y": 0.5
  },
  {
    "time": 161.162,
    "x": -0.629,
    "y": 0.5
  },
  {
    "time": 161.178,
    "x": -0.882,
    "y": 0.5
  },
  {
    "time": 161.194,
    "x": -1.144,
    "y": 0.5
  },
  {
    "time": 161.211,
    "x": -1.404,
    "y": 0.5
  },
  {
    "time": 161.228,
    "x": -1.669,
    "y": 0.5
  },
  {
    "time": 161.243,
    "x": -1.915,
    "y": 0.5
  },
  {
    "time": 161.26,
    "x": -2.176,
    "y": 0.5
  },
  {
    "time": 161.276,
    "x": -2.417,
    "y": 0.5
  },
  {
    "time": 161.293,
    "x": -2.669,
    "y": 0.5
  },
  {
    "time": 161.308,
    "x": -2.898,
    "y": 0.5
  },
  {
    "time": 161.325,
    "x": -3.146,
    "y": 0.5
  },
  {
    "time": 161.34,
    "x": -3.37,
    "y": 0.5
  },
  {
    "time": 161.356,
    "x": -3.605,
    "y": 0.5
  },
  {
    "time": 161.372,
    "x": -3.832,
    "y": 0.5
  },
  {
    "time": 161.389,
    "x": -4.059,
    "y": 0.5
  },
  {
    "time": 161.404,
    "x": -4.268,
    "y": 0.5
  },
  {
    "time": 161.421,
    "x": -4.492,
    "y": 0.5
  },
  {
    "time": 161.436,
    "x": -4.698,
    "y": 0.5
  },
  {
    "time": 161.452,
    "x": -4.902,
    "y": 0.5
  },
  {
    "time": 161.469,
    "x": -5.105,
    "y": 0.5
  },
  {
    "time": 161.485,
    "x": -5.302,
    "y": 0.5
  },
  {
    "time": 161.502,
    "x": -5.504,
    "y": 0.5
  },
  {
    "time": 161.518,
    "x": -5.691,
    "y": 0.5
  },
  {
    "time": 161.535,
    "x": -5.872,
    "y": 0.5
  },
  {
    "time": 161.55,
    "x": -6.034,
    "y": 0.5
  },
  {
    "time": 161.566,
    "x": -6.201,
    "y": 0.5
  },
  {
    "time": 161.582,
    "x": -6.361,
    "y": 0.5
  },
  {
    "time": 161.599,
    "x": -6.519,
    "y": 0.5
  },
  {
    "time": 161.615,
    "x": -6.664,
    "y": 0.5
  },
  {
    "time": 161.632,
    "x": -6.808,
    "y": 0.5
  },
  {
    "time": 161.647,
    "x": -6.934,
    "y": 0.5
  },
  {
    "time": 161.663,
    "x": -7.062,
    "y": 0.5
  },
  {
    "time": 161.679,
    "x": -7.177,
    "y": 0.5
  },
  {
    "time": 161.696,
    "x": -7.29,
    "y": 0.5
  },
  {
    "time": 161.712,
    "x": -7.395,
    "y": 0.5
  },
  {
    "time": 161.729,
    "x": -7.492,
    "y": 0.5
  },
  {
    "time": 161.746,
    "x": -7.582,
    "y": 0.5
  },
  {
    "time": 161.761,
    "x": -7.659,
    "y": 0.5
  },
  {
    "time": 161.778,
    "x": -7.73,
    "y": 0.5
  },
  {
    "time": 161.793,
    "x": -7.789,
    "y": 0.5
  },
  {
    "time": 161.81,
    "x": -7.846,
    "y": 0.5
  },
  {
    "time": 161.826,
    "x": -7.892,
    "y": 0.5
  },
  {
    "time": 161.842,
    "x": -7.93,
    "y": 0.5
  },
  {
    "time": 161.858,
    "x": -7.961,
    "y": 0.5
  },
  {
    "time": 161.874,
    "x": -7.982,
    "y": 0.5
  },
  {
    "time": 161.89,
    "x": -7.995,
    "y": 0.5
  },
  {
    "time": 161.907,
    "x": -8.0,
    "y": 0.5
  },
  {
    "time": 161.922,
    "x": -7.997,
    "y": 0.5
  },
  {
    "time": 161.938,
    "x": -7.986,
    "y": 0.5
  },
  {
    "time": 161.955,
    "x": -7.965,
    "y": 0.5
  },
  {
    "time": 161.971,
    "x": -7.937,
    "y": 0.5
  },
  {
    "time": 161.987,
    "x": -7.9,
    "y": 0.5
  },
  {
    "time": 162.004,
    "x": -7.854,
    "y": 0.5
  },
  {
    "time": 162.02,
    "x": -7.801,
    "y": 0.5
  },
  {
    "time": 162.037,
    "x": -7.736,
    "y": 0.5
  },
  {
    "time": 162.053,
    "x": -7.667,
    "y": 0.5
  },
  {
    "time": 162.069,
    "x": -7.587,
    "y": 0.5
  },
  {
    "time": 162.086,
    "x": -7.499,
    "y": 0.5
  },
  {
    "time": 162.102,
    "x": -7.403,
    "y": 0.5
  },
  {
    "time": 162.118,
    "x": -7.303,
    "y": 0.5
  },
  {
    "time": 162.134,
    "x": -7.193,
    "y": 0.5
  },
  {
    "time": 162.151,
    "x": -7.076,
    "y": 0.5
  },
  {
    "time": 162.167,
    "x": -6.954,
    "y": 0.5
  },
  {
    "time": 162.182,
    "x": -6.828,
    "y": 0.5
  },
  {
    "time": 162.198,
    "x": -6.69,
    "y": 0.5
  },
  {
    "time": 162.215,
    "x": -6.54,
    "y": 0.5
  },
  {
    "time": 162.232,
    "x": -6.379,
    "y": 0.5
  },
  {
    "time": 162.249,
    "x": -6.213,
    "y": 0.5
  },
  {
    "time": 162.264,
    "x": -6.051,
    "y": 0.5
  },
  {
    "time": 162.281,
    "x": -5.876,
    "y": 0.5
  }
]